{"speedlogs":[
{"bytes_received": 117115656, "timestamp": "2017-12-16T05:00:57.898362", "bytes_sent": 15122432, "upload": 11927800.492852928, "server": {"latency": 21.753, "name": "Washington, DC", "url": "http://was.speedtest.sbcglobal.net/speedtest/upload.php", "country": "United States", "lon": "-77.0164", "cc": "US", "host": "was.speedtest.sbcglobal.net:8080", "sponsor": "AT&T", "lat": "38.9047", "id": "5113", "d": 14.199124910496671}, "download": 93176921.00358354, "ping": 21.753},{"bytes_received": 117074202, "timestamp": "2017-12-16T05:15:57.957857", "bytes_sent": 14983168, "upload": 11671387.210579323, "server": {"latency": 20.031, "name": "Washington, DC", "url": "http://was.speedtest.sbcglobal.net/speedtest/upload.php", "country": "United States", "lon": "-77.0164", "cc": "US", "host": "was.speedtest.sbcglobal.net:8080", "sponsor": "AT&T", "lat": "38.9047", "id": "5113", "d": 14.199124910496671}, "download": 93340322.84259567, "ping": 20.031},{"bytes_received": 117107876, "timestamp": "2017-12-16T05:30:57.914490", "bytes_sent": 15040512, "upload": 11780866.721815933, "server": {"latency": 21.173, "name": "Washington, DC", "url": "http://was.speedtest.sbcglobal.net/speedtest/upload.php", "country": "United States", "lon": "-77.0164", "cc": "US", "host": "was.speedtest.sbcglobal.net:8080", "sponsor": "AT&T", "lat": "38.9047", "id": "5113", "d": 14.199124910496671}, "download": 93321385.89396389, "ping": 21.173},{"bytes_received": 117063962, "timestamp": "2017-12-16T05:45:57.979566", "bytes_sent": 14950400, "upload": 11720937.619831258, "server": {"latency": 22.988, "name": "Washington, DC", "url": "http://was.speedtest.sbcglobal.net/speedtest/upload.php", "country": "United States", "lon": "-77.0164", "cc": "US", "host": "was.speedtest.sbcglobal.net:8080", "sponsor": "AT&T", "lat": "38.9047", "id": "5113", "d": 14.199124910496671}, "download": 93284151.75848596, "ping": 22.988},{"bytes_received": 117150708, "timestamp": "2017-12-16T06:00:57.896748", "bytes_sent": 14835712, "upload": 11705989.819197815, "server": {"latency": 21.424, "name": "Fairfax, VA", "url": "http://speedtest.rdc.dc.cox.net/speedtest/upload.php", "country": "United States", "lon": "-77.3063", "cc": "US", "host": "speedtest.rd.dc.cox.net:8080", "sponsor": "CCI - Nova", "lat": "38.8462", "id": "14122", "d": 15.87758843134814}, "download": 92917407.46530372, "ping": 21.424},{"bytes_received": 117166362, "timestamp": "2017-12-16T06:15:57.891076", "bytes_sent": 15040512, "upload": 11870685.63652088, "server": {"latency": 22.135, "name": "Fairfax, VA", "url": "http://speedtest.rdc.dc.cox.net/speedtest/upload.php", "country": "United States", "lon": "-77.3063", "cc": "US", "host": "speedtest.rd.dc.cox.net:8080", "sponsor": "CCI - Nova", "lat": "38.8462", "id": "14122", "d": 15.87758843134814}, "download": 93134542.5794454, "ping": 22.135},{"bytes_received": 96733136, "timestamp": "2017-12-16T06:30:57.887239", "bytes_sent": 15065088, "upload": 11884768.562275283, "server": {"latency": 21.032, "name": "Fairfax, VA", "url": "http://speedtest.rdc.dc.cox.net/speedtest/upload.php", "country": "United States", "lon": "-77.3063", "cc": "US", "host": "speedtest.rd.dc.cox.net:8080", "sponsor": "CCI - Nova", "lat": "38.8462", "id": "14122", "d": 15.87758843134814}, "download": 76966884.3447708, "ping": 21.032},{"bytes_received": 117217562, "timestamp": "2017-12-16T06:45:57.938144", "bytes_sent": 14032896, "upload": 11087300.743356809, "server": {"latency": 21.317, "name": "Fairfax, VA", "url": "http://speedtest.rdc.dc.cox.net/speedtest/upload.php", "country": "United States", "lon": "-77.3063", "cc": "US", "host": "speedtest.rd.dc.cox.net:8080", "sponsor": "CCI - Nova", "lat": "38.8462", "id": "14122", "d": 15.87758843134814}, "download": 93236208.58656994, "ping": 21.317},{"bytes_received": 117112208, "timestamp": "2017-12-16T07:00:57.860248", "bytes_sent": 15089664, "upload": 11866821.828255126, "server": {"latency": 21.093, "name": "Washington, DC", "url": "http://was.speedtest.sbcglobal.net/speedtest/upload.php", "country": "United States", "lon": "-77.0164", "cc": "US", "host": "was.speedtest.sbcglobal.net:8080", "sponsor": "AT&T", "lat": "38.9047", "id": "5113", "d": 14.199124910496671}, "download": 93332489.53464395, "ping": 21.093}]}
