{"speedlogs":[
{"bytes_received": 117233122, "timestamp": "2017-06-29T04:00:01.056946", "bytes_sent": 15073280, "upload": 10277669.274675341, "server": {"latency": 22.461, "name": "Manassas, VA", "url": "http://stosat-rstn-01.sys.comcast.net/speedtest/upload.php", "country": "United States", "lon": "-77.4764", "cc": "US", "host": "stosat-rstn-01.sys.comcast.net:8080", "sponsor": "Comcast", "url2": "http://a-stosat-rstn-01.sys.comcast.net/speedtest/upload.php", "lat": "38.7514", "id": "9839", "d": 30.88789265402574}, "download": 93261546.96785474, "ping": 22.461},{"bytes_received": 117168728, "timestamp": "2017-06-29T04:15:01.106229", "bytes_sent": 15073280, "upload": 11898934.230692526, "server": {"latency": 21.249, "name": "Manassas, VA", "url": "http://stosat-rstn-01.sys.comcast.net/speedtest/upload.php", "country": "United States", "lon": "-77.4764", "cc": "US", "host": "stosat-rstn-01.sys.comcast.net:8080", "sponsor": "Comcast", "url2": "http://a-stosat-rstn-01.sys.comcast.net/speedtest/upload.php", "lat": "38.7514", "id": "9839", "d": 30.88789265402574}, "download": 93463294.44624025, "ping": 21.249},{"bytes_received": 117136136, "timestamp": "2017-06-29T04:30:01.105744", "bytes_sent": 15073280, "upload": 11808949.546172885, "server": {"latency": 23.076, "name": "Manassas, VA", "url": "http://stosat-rstn-01.sys.comcast.net/speedtest/upload.php", "country": "United States", "lon": "-77.4764", "cc": "US", "host": "stosat-rstn-01.sys.comcast.net:8080", "sponsor": "Comcast", "url2": "http://a-stosat-rstn-01.sys.comcast.net/speedtest/upload.php", "lat": "38.7514", "id": "9839", "d": 30.88789265402574}, "download": 93334917.47971828, "ping": 23.076},{"bytes_received": 117133182, "timestamp": "2017-06-29T04:45:01.067989", "bytes_sent": 15032320, "upload": 11833262.591380108, "server": {"latency": 25.36, "name": "Manassas, VA", "url": "http://stosat-rstn-01.sys.comcast.net/speedtest/upload.php", "country": "United States", "lon": "-77.4764", "cc": "US", "host": "stosat-rstn-01.sys.comcast.net:8080", "sponsor": "Comcast", "url2": "http://a-stosat-rstn-01.sys.comcast.net/speedtest/upload.php", "lat": "38.7514", "id": "9839", "d": 30.88789265402574}, "download": 93317419.69526629, "ping": 25.36},{"bytes_received": 117127274, "timestamp": "2017-06-29T05:00:01.138042", "bytes_sent": 15065088, "upload": 11873616.983170085, "server": {"latency": 23.967, "name": "Manassas, VA", "url": "http://stosat-rstn-01.sys.comcast.net/speedtest/upload.php", "country": "United States", "lon": "-77.4764", "cc": "US", "host": "stosat-rstn-01.sys.comcast.net:8080", "sponsor": "Comcast", "url2": "http://a-stosat-rstn-01.sys.comcast.net/speedtest/upload.php", "lat": "38.7514", "id": "9839", "d": 30.88789265402574}, "download": 93277211.8092736, "ping": 23.967},{"bytes_received": 117113196, "timestamp": "2017-06-29T05:15:01.143280", "bytes_sent": 15106048, "upload": 11965230.144752614, "server": {"latency": 22.888, "name": "Manassas, VA", "url": "http://stosat-rstn-01.sys.comcast.net/speedtest/upload.php", "country": "United States", "lon": "-77.4764", "cc": "US", "host": "stosat-rstn-01.sys.comcast.net:8080", "sponsor": "Comcast", "url2": "http://a-stosat-rstn-01.sys.comcast.net/speedtest/upload.php", "lat": "38.7514", "id": "9839", "d": 30.88789265402574}, "download": 93344231.18259265, "ping": 22.888},{"bytes_received": 117109748, "timestamp": "2017-06-29T05:30:01.144517", "bytes_sent": 15097856, "upload": 8649345.90126575, "server": {"latency": 23.169, "name": "Manassas, VA", "url": "http://stosat-rstn-01.sys.comcast.net/speedtest/upload.php", "country": "United States", "lon": "-77.4764", "cc": "US", "host": "stosat-rstn-01.sys.comcast.net:8080", "sponsor": "Comcast", "url2": "http://a-stosat-rstn-01.sys.comcast.net/speedtest/upload.php", "lat": "38.7514", "id": "9839", "d": 30.88789265402574}, "download": 93157165.31570506, "ping": 23.169},{"bytes_received": 117112702, "timestamp": "2017-06-29T05:45:01.067533", "bytes_sent": 15015936, "upload": 11905069.939274058, "server": {"latency": 23.143, "name": "Manassas, VA", "url": "http://stosat-rstn-01.sys.comcast.net/speedtest/upload.php", "country": "United States", "lon": "-77.4764", "cc": "US", "host": "stosat-rstn-01.sys.comcast.net:8080", "sponsor": "Comcast", "url2": "http://a-stosat-rstn-01.sys.comcast.net/speedtest/upload.php", "lat": "38.7514", "id": "9839", "d": 30.88789265402574}, "download": 93112713.69896345, "ping": 23.143},{"bytes_received": 117189702, "timestamp": "2017-06-29T06:00:01.086669", "bytes_sent": 15081472, "upload": 11931644.467850404, "server": {"latency": 21.069, "name": "Manassas, VA", "url": "http://stosat-rstn-01.sys.comcast.net/speedtest/upload.php", "country": "United States", "lon": "-77.4764", "cc": "US", "host": "stosat-rstn-01.sys.comcast.net:8080", "sponsor": "Comcast", "url2": "http://a-stosat-rstn-01.sys.comcast.net/speedtest/upload.php", "lat": "38.7514", "id": "9839", "d": 30.88789265402574}, "download": 92961016.35192133, "ping": 21.069},{"bytes_received": 117138008, "timestamp": "2017-06-29T06:15:01.054904", "bytes_sent": 15097856, "upload": 11808926.768003207, "server": {"latency": 24.424, "name": "Manassas, VA", "url": "http://stosat-rstn-01.sys.comcast.net/speedtest/upload.php", "country": "United States", "lon": "-77.4764", "cc": "US", "host": "stosat-rstn-01.sys.comcast.net:8080", "sponsor": "Comcast", "url2": "http://a-stosat-rstn-01.sys.comcast.net/speedtest/upload.php", "lat": "38.7514", "id": "9839", "d": 30.88789265402574}, "download": 93487841.66806637, "ping": 24.424},{"bytes_received": 117156616, "timestamp": "2017-06-29T06:30:01.078522", "bytes_sent": 14934016, "upload": 11878795.725856736, "server": {"latency": 23.28, "name": "Manassas, VA", "url": "http://stosat-rstn-01.sys.comcast.net/speedtest/upload.php", "country": "United States", "lon": "-77.4764", "cc": "US", "host": "stosat-rstn-01.sys.comcast.net:8080", "sponsor": "Comcast", "url2": "http://a-stosat-rstn-01.sys.comcast.net/speedtest/upload.php", "lat": "38.7514", "id": "9839", "d": 30.88789265402574}, "download": 93368288.49371009, "ping": 23.28},{"bytes_received": 117099508, "timestamp": "2017-06-29T06:45:01.065948", "bytes_sent": 14942208, "upload": 11759929.756825026, "server": {"latency": 23.816, "name": "Manassas, VA", "url": "http://stosat-rstn-01.sys.comcast.net/speedtest/upload.php", "country": "United States", "lon": "-77.4764", "cc": "US", "host": "stosat-rstn-01.sys.comcast.net:8080", "sponsor": "Comcast", "url2": "http://a-stosat-rstn-01.sys.comcast.net/speedtest/upload.php", "lat": "38.7514", "id": "9839", "d": 30.88789265402574}, "download": 93113568.44060464, "ping": 23.816},{"bytes_received": 117143422, "timestamp": "2017-06-29T07:00:01.109959", "bytes_sent": 14983168, "upload": 11865379.382176695, "server": {"latency": 47.141, "name": "Manassas, VA", "url": "http://stosat-rstn-01.sys.comcast.net/speedtest/upload.php", "country": "United States", "lon": "-77.4764", "cc": "US", "host": "stosat-rstn-01.sys.comcast.net:8080", "sponsor": "Comcast", "url2": "http://a-stosat-rstn-01.sys.comcast.net/speedtest/upload.php", "lat": "38.7514", "id": "9839", "d": 30.88789265402574}, "download": 93194377.82336988, "ping": 47.141},{"bytes_received": 117058548, "timestamp": "2017-06-29T07:15:01.163074", "bytes_sent": 14966784, "upload": 11805760.398683552, "server": {"latency": 23.291, "name": "Manassas, VA", "url": "http://stosat-rstn-01.sys.comcast.net/speedtest/upload.php", "country": "United States", "lon": "-77.4764", "cc": "US", "host": "stosat-rstn-01.sys.comcast.net:8080", "sponsor": "Comcast", "url2": "http://a-stosat-rstn-01.sys.comcast.net/speedtest/upload.php", "lat": "38.7514", "id": "9839", "d": 30.88789265402574}, "download": 93255073.19504142, "ping": 23.291},{"bytes_received": 117097048, "timestamp": "2017-06-29T07:30:01.091252", "bytes_sent": 14983168, "upload": 11914783.569616761, "server": {"latency": 23.164, "name": "Manassas, VA", "url": "http://stosat-rstn-01.sys.comcast.net/speedtest/upload.php", "country": "United States", "lon": "-77.4764", "cc": "US", "host": "stosat-rstn-01.sys.comcast.net:8080", "sponsor": "Comcast", "url2": "http://a-stosat-rstn-01.sys.comcast.net/speedtest/upload.php", "lat": "38.7514", "id": "9839", "d": 30.88789265402574}, "download": 93385827.72677854, "ping": 23.164},{"bytes_received": 117145882, "timestamp": "2017-06-29T07:45:01.049989", "bytes_sent": 15130624, "upload": 11861698.719504587, "server": {"latency": 23.627, "name": "Manassas, VA", "url": "http://stosat-rstn-01.sys.comcast.net/speedtest/upload.php", "country": "United States", "lon": "-77.4764", "cc": "US", "host": "stosat-rstn-01.sys.comcast.net:8080", "sponsor": "Comcast", "url2": "http://a-stosat-rstn-01.sys.comcast.net/speedtest/upload.php", "lat": "38.7514", "id": "9839", "d": 30.88789265402574}, "download": 93254396.08829491, "ping": 23.627},{"bytes_received": 117145882, "timestamp": "2017-06-29T08:00:01.178004", "bytes_sent": 15065088, "upload": 11978760.217482328, "server": {"latency": 23.3, "name": "Manassas, VA", "url": "http://stosat-rstn-01.sys.comcast.net/speedtest/upload.php", "country": "United States", "lon": "-77.4764", "cc": "US", "host": "stosat-rstn-01.sys.comcast.net:8080", "sponsor": "Comcast", "url2": "http://a-stosat-rstn-01.sys.comcast.net/speedtest/upload.php", "lat": "38.7514", "id": "9839", "d": 30.88789265402574}, "download": 93452106.47203267, "ping": 23.3},{"bytes_received": 117153662, "timestamp": "2017-06-29T08:15:01.058455", "bytes_sent": 14934016, "upload": 11737594.665290486, "server": {"latency": 23.775, "name": "Manassas, VA", "url": "http://stosat-rstn-01.sys.comcast.net/speedtest/upload.php", "country": "United States", "lon": "-77.4764", "cc": "US", "host": "stosat-rstn-01.sys.comcast.net:8080", "sponsor": "Comcast", "url2": "http://a-stosat-rstn-01.sys.comcast.net/speedtest/upload.php", "lat": "38.7514", "id": "9839", "d": 30.88789265402574}, "download": 93284150.00505297, "ping": 23.775},{"bytes_received": 117133676, "timestamp": "2017-06-29T08:30:01.052968", "bytes_sent": 15032320, "upload": 11944581.491864499, "server": {"latency": 24.159, "name": "Manassas, VA", "url": "http://stosat-rstn-01.sys.comcast.net/speedtest/upload.php", "country": "United States", "lon": "-77.4764", "cc": "US", "host": "stosat-rstn-01.sys.comcast.net:8080", "sponsor": "Comcast", "url2": "http://a-stosat-rstn-01.sys.comcast.net/speedtest/upload.php", "lat": "38.7514", "id": "9839", "d": 30.88789265402574}, "download": 93304286.57200494, "ping": 24.159},{"bytes_received": 117151202, "timestamp": "2017-06-29T08:45:01.056487", "bytes_sent": 15097856, "upload": 11866821.707528232, "server": {"latency": 23.738, "name": "Manassas, VA", "url": "http://stosat-rstn-01.sys.comcast.net/speedtest/upload.php", "country": "United States", "lon": "-77.4764", "cc": "US", "host": "stosat-rstn-01.sys.comcast.net:8080", "sponsor": "Comcast", "url2": "http://a-stosat-rstn-01.sys.comcast.net/speedtest/upload.php", "lat": "38.7514", "id": "9839", "d": 30.88789265402574}, "download": 93193644.67409468, "ping": 23.738},{"bytes_received": 117071742, "timestamp": "2017-06-29T09:00:01.163307", "bytes_sent": 15040512, "upload": 9075131.120509828, "server": {"latency": 24.117, "name": "Manassas, VA", "url": "http://stosat-rstn-01.sys.comcast.net/speedtest/upload.php", "country": "United States", "lon": "-77.4764", "cc": "US", "host": "stosat-rstn-01.sys.comcast.net:8080", "sponsor": "Comcast", "url2": "http://a-stosat-rstn-01.sys.comcast.net/speedtest/upload.php", "lat": "38.7514", "id": "9839", "d": 30.88789265402574}, "download": 93230582.29851514, "ping": 24.117},{"bytes_received": 117191668, "timestamp": "2017-06-29T09:15:01.143911", "bytes_sent": 14974976, "upload": 11816939.144391363, "server": {"latency": 21.606, "name": "Manassas, VA", "url": "http://stosat-rstn-01.sys.comcast.net/speedtest/upload.php", "country": "United States", "lon": "-77.4764", "cc": "US", "host": "stosat-rstn-01.sys.comcast.net:8080", "sponsor": "Comcast", "url2": "http://a-stosat-rstn-01.sys.comcast.net/speedtest/upload.php", "lat": "38.7514", "id": "9839", "d": 30.88789265402574}, "download": 93431080.67882283, "ping": 21.606},{"bytes_received": 117147754, "timestamp": "2017-06-29T09:30:01.079647", "bytes_sent": 14311424, "upload": 9368422.809660587, "server": {"latency": 20.237, "name": "Manassas, VA", "url": "http://stosat-rstn-01.sys.comcast.net/speedtest/upload.php", "country": "United States", "lon": "-77.4764", "cc": "US", "host": "stosat-rstn-01.sys.comcast.net:8080", "sponsor": "Comcast", "url2": "http://a-stosat-rstn-01.sys.comcast.net/speedtest/upload.php", "lat": "38.7514", "id": "9839", "d": 30.88789265402574}, "download": 92926809.52982129, "ping": 20.237},{"bytes_received": 117200036, "timestamp": "2017-06-29T09:45:01.043774", "bytes_sent": 15073280, "upload": 11848488.73984876, "server": {"latency": 20.345, "name": "Manassas, VA", "url": "http://stosat-rstn-01.sys.comcast.net/speedtest/upload.php", "country": "United States", "lon": "-77.4764", "cc": "US", "host": "stosat-rstn-01.sys.comcast.net:8080", "sponsor": "Comcast", "url2": "http://a-stosat-rstn-01.sys.comcast.net/speedtest/upload.php", "lat": "38.7514", "id": "9839", "d": 30.88789265402574}, "download": 81754168.75572024, "ping": 20.345},{"bytes_received": 117209688, "timestamp": "2017-06-29T10:00:01.056981", "bytes_sent": 14721024, "upload": 11715090.121530747, "server": {"latency": 20.62, "name": "Manassas, VA", "url": "http://stosat-rstn-01.sys.comcast.net/speedtest/upload.php", "country": "United States", "lon": "-77.4764", "cc": "US", "host": "stosat-rstn-01.sys.comcast.net:8080", "sponsor": "Comcast", "url2": "http://a-stosat-rstn-01.sys.comcast.net/speedtest/upload.php", "lat": "38.7514", "id": "9839", "d": 30.88789265402574}, "download": 92924728.97033654, "ping": 20.62},{"bytes_received": 117191668, "timestamp": "2017-06-29T10:15:01.046711", "bytes_sent": 15089664, "upload": 11918215.030161217, "server": {"latency": 20.845, "name": "Manassas, VA", "url": "http://stosat-rstn-01.sys.comcast.net/speedtest/upload.php", "country": "United States", "lon": "-77.4764", "cc": "US", "host": "stosat-rstn-01.sys.comcast.net:8080", "sponsor": "Comcast", "url2": "http://a-stosat-rstn-01.sys.comcast.net/speedtest/upload.php", "lat": "38.7514", "id": "9839", "d": 30.88789265402574}, "download": 93359645.2336336, "ping": 20.845},{"bytes_received": 117245822, "timestamp": "2017-06-29T10:30:01.090339", "bytes_sent": 15048704, "upload": 11866941.238621794, "server": {"latency": 20.025, "name": "Manassas, VA", "url": "http://stosat-rstn-01.sys.comcast.net/speedtest/upload.php", "country": "United States", "lon": "-77.4764", "cc": "US", "host": "stosat-rstn-01.sys.comcast.net:8080", "sponsor": "Comcast", "url2": "http://a-stosat-rstn-01.sys.comcast.net/speedtest/upload.php", "lat": "38.7514", "id": "9839", "d": 30.88789265402574}, "download": 92974401.40547176, "ping": 20.025},{"bytes_received": 116961562, "timestamp": "2017-06-29T10:45:01.087822", "bytes_sent": 14917632, "upload": 11822708.467452213, "server": {"latency": 19.685, "name": "Manassas, VA", "url": "http://stosat-rstn-01.sys.comcast.net/speedtest/upload.php", "country": "United States", "lon": "-77.4764", "cc": "US", "host": "stosat-rstn-01.sys.comcast.net:8080", "sponsor": "Comcast", "url2": "http://a-stosat-rstn-01.sys.comcast.net/speedtest/upload.php", "lat": "38.7514", "id": "9839", "d": 30.88789265402574}, "download": 92649628.41841899, "ping": 19.685},{"bytes_received": 117297022, "timestamp": "2017-06-29T11:00:01.042501", "bytes_sent": 15048704, "upload": 11952374.324876508, "server": {"latency": 18.834, "name": "Manassas, VA", "url": "http://stosat-rstn-01.sys.comcast.net/speedtest/upload.php", "country": "United States", "lon": "-77.4764", "cc": "US", "host": "stosat-rstn-01.sys.comcast.net:8080", "sponsor": "Comcast", "url2": "http://a-stosat-rstn-01.sys.comcast.net/speedtest/upload.php", "lat": "38.7514", "id": "9839", "d": 30.88789265402574}, "download": 93475232.32339759, "ping": 18.834},{"bytes_received": 117232628, "timestamp": "2017-06-29T11:15:01.116902", "bytes_sent": 15106048, "upload": 11841741.73127272, "server": {"latency": 21.546, "name": "Manassas, VA", "url": "http://stosat-rstn-01.sys.comcast.net/speedtest/upload.php", "country": "United States", "lon": "-77.4764", "cc": "US", "host": "stosat-rstn-01.sys.comcast.net:8080", "sponsor": "Comcast", "url2": "http://a-stosat-rstn-01.sys.comcast.net/speedtest/upload.php", "lat": "38.7514", "id": "9839", "d": 30.88789265402574}, "download": 93413792.78884816, "ping": 21.546},{"bytes_received": 117227802, "timestamp": "2017-06-29T11:30:01.082763", "bytes_sent": 15065088, "upload": 11813482.942678977, "server": {"latency": 21.943, "name": "Manassas, VA", "url": "http://stosat-rstn-01.sys.comcast.net/speedtest/upload.php", "country": "United States", "lon": "-77.4764", "cc": "US", "host": "stosat-rstn-01.sys.comcast.net:8080", "sponsor": "Comcast", "url2": "http://a-stosat-rstn-01.sys.comcast.net/speedtest/upload.php", "lat": "38.7514", "id": "9839", "d": 30.88789265402574}, "download": 93434431.85257971, "ping": 21.943},{"bytes_received": 117204368, "timestamp": "2017-06-29T11:45:01.057033", "bytes_sent": 15056896, "upload": 11860140.461905876, "server": {"latency": 20.474, "name": "Manassas, VA", "url": "http://stosat-rstn-01.sys.comcast.net/speedtest/upload.php", "country": "United States", "lon": "-77.4764", "cc": "US", "host": "stosat-rstn-01.sys.comcast.net:8080", "sponsor": "Comcast", "url2": "http://a-stosat-rstn-01.sys.comcast.net/speedtest/upload.php", "lat": "38.7514", "id": "9839", "d": 30.88789265402574}, "download": 93191271.69780986, "ping": 20.474},{"bytes_received": 117171682, "timestamp": "2017-06-29T12:00:01.117354", "bytes_sent": 15073280, "upload": 11929628.948213499, "server": {"latency": 19.897, "name": "Manassas, VA", "url": "http://stosat-rstn-01.sys.comcast.net/speedtest/upload.php", "country": "United States", "lon": "-77.4764", "cc": "US", "host": "stosat-rstn-01.sys.comcast.net:8080", "sponsor": "Comcast", "url2": "http://a-stosat-rstn-01.sys.comcast.net/speedtest/upload.php", "lat": "38.7514", "id": "9839", "d": 30.88789265402574}, "download": 93383682.20870063, "ping": 19.897},{"bytes_received": 117180934, "timestamp": "2017-06-29T12:15:01.045069", "bytes_sent": 15106048, "upload": 11961334.170583362, "server": {"latency": 19.806, "name": "Manassas, VA", "url": "http://stosat-rstn-01.sys.comcast.net/speedtest/upload.php", "country": "United States", "lon": "-77.4764", "cc": "US", "host": "stosat-rstn-01.sys.comcast.net:8080", "sponsor": "Comcast", "url2": "http://a-stosat-rstn-01.sys.comcast.net/speedtest/upload.php", "lat": "38.7514", "id": "9839", "d": 30.88789265402574}, "download": 93457905.25769839, "ping": 19.806},{"bytes_received": 116987362, "timestamp": "2017-06-29T12:30:01.050547", "bytes_sent": 15089664, "upload": 11585698.318817254, "server": {"latency": 20.036, "name": "Manassas, VA", "url": "http://stosat-rstn-01.sys.comcast.net/speedtest/upload.php", "country": "United States", "lon": "-77.4764", "cc": "US", "host": "stosat-rstn-01.sys.comcast.net:8080", "sponsor": "Comcast", "url2": "http://a-stosat-rstn-01.sys.comcast.net/speedtest/upload.php", "lat": "38.7514", "id": "9839", "d": 30.88789265402574}, "download": 92963270.80858217, "ping": 20.036},{"bytes_received": 117176602, "timestamp": "2017-06-29T12:45:01.054096", "bytes_sent": 15032320, "upload": 11893322.832510643, "server": {"latency": 21.643, "name": "Manassas, VA", "url": "http://stosat-rstn-01.sys.comcast.net/speedtest/upload.php", "country": "United States", "lon": "-77.4764", "cc": "US", "host": "stosat-rstn-01.sys.comcast.net:8080", "sponsor": "Comcast", "url2": "http://a-stosat-rstn-01.sys.comcast.net/speedtest/upload.php", "lat": "38.7514", "id": "9839", "d": 30.88789265402574}, "download": 93245197.08280146, "ping": 21.643},{"bytes_received": 117204368, "timestamp": "2017-06-29T13:00:01.046070", "bytes_sent": 15081472, "upload": 11841064.016731963, "server": {"latency": 19.682, "name": "Manassas, VA", "url": "http://stosat-rstn-01.sys.comcast.net/speedtest/upload.php", "country": "United States", "lon": "-77.4764", "cc": "US", "host": "stosat-rstn-01.sys.comcast.net:8080", "sponsor": "Comcast", "url2": "http://a-stosat-rstn-01.sys.comcast.net/speedtest/upload.php", "lat": "38.7514", "id": "9839", "d": 30.88789265402574}, "download": 92927554.86785577, "ping": 19.682},{"bytes_received": 117147754, "timestamp": "2017-06-29T13:15:01.058221", "bytes_sent": 13910016, "upload": 10918150.645913457, "server": {"latency": 19.255, "name": "Manassas, VA", "url": "http://stosat-rstn-01.sys.comcast.net/speedtest/upload.php", "country": "United States", "lon": "-77.4764", "cc": "US", "host": "stosat-rstn-01.sys.comcast.net:8080", "sponsor": "Comcast", "url2": "http://a-stosat-rstn-01.sys.comcast.net/speedtest/upload.php", "lat": "38.7514", "id": "9839", "d": 30.88789265402574}, "download": 93201662.53754853, "ping": 19.255},{"bytes_received": 117142928, "timestamp": "2017-06-29T13:30:01.065421", "bytes_sent": 13877248, "upload": 9049961.209141051, "server": {"latency": 22.116, "name": "Manassas, VA", "url": "http://stosat-rstn-01.sys.comcast.net/speedtest/upload.php", "country": "United States", "lon": "-77.4764", "cc": "US", "host": "stosat-rstn-01.sys.comcast.net:8080", "sponsor": "Comcast", "url2": "http://a-stosat-rstn-01.sys.comcast.net/speedtest/upload.php", "lat": "38.7514", "id": "9839", "d": 30.88789265402574}, "download": 93348761.81821524, "ping": 22.116},{"bytes_received": 117119988, "timestamp": "2017-06-29T13:45:01.174877", "bytes_sent": 13713408, "upload": 10751017.57076828, "server": {"latency": 23.036, "name": "Manassas, VA", "url": "http://stosat-rstn-01.sys.comcast.net/speedtest/upload.php", "country": "United States", "lon": "-77.4764", "cc": "US", "host": "stosat-rstn-01.sys.comcast.net:8080", "sponsor": "Comcast", "url2": "http://a-stosat-rstn-01.sys.comcast.net/speedtest/upload.php", "lat": "38.7514", "id": "9839", "d": 30.88789265402574}, "download": 93470885.40984826, "ping": 23.036},{"bytes_received": 117160948, "timestamp": "2017-06-29T14:00:01.076279", "bytes_sent": 15065088, "upload": 11818689.337097604, "server": {"latency": 20.7, "name": "Manassas, VA", "url": "http://stosat-rstn-01.sys.comcast.net/speedtest/upload.php", "country": "United States", "lon": "-77.4764", "cc": "US", "host": "stosat-rstn-01.sys.comcast.net:8080", "sponsor": "Comcast", "url2": "http://a-stosat-rstn-01.sys.comcast.net/speedtest/upload.php", "lat": "38.7514", "id": "9839", "d": 30.88789265402574}, "download": 93369713.980984, "ping": 20.7},{"bytes_received": 117227802, "timestamp": "2017-06-29T14:15:01.068215", "bytes_sent": 13795328, "upload": 10829265.181214495, "server": {"latency": 19.691, "name": "Manassas, VA", "url": "http://stosat-rstn-01.sys.comcast.net/speedtest/upload.php", "country": "United States", "lon": "-77.4764", "cc": "US", "host": "stosat-rstn-01.sys.comcast.net:8080", "sponsor": "Comcast", "url2": "http://a-stosat-rstn-01.sys.comcast.net/speedtest/upload.php", "lat": "38.7514", "id": "9839", "d": 30.88789265402574}, "download": 93523956.69742523, "ping": 19.691},{"bytes_received": 117099508, "timestamp": "2017-06-29T14:30:01.117857", "bytes_sent": 14974976, "upload": 11931821.439512147, "server": {"latency": 20.514, "name": "Manassas, VA", "url": "http://stosat-rstn-01.sys.comcast.net/speedtest/upload.php", "country": "United States", "lon": "-77.4764", "cc": "US", "host": "stosat-rstn-01.sys.comcast.net:8080", "sponsor": "Comcast", "url2": "http://a-stosat-rstn-01.sys.comcast.net/speedtest/upload.php", "lat": "38.7514", "id": "9839", "d": 30.88789265402574}, "download": 93148538.31416108, "ping": 20.514},{"bytes_received": 117237948, "timestamp": "2017-06-29T14:45:01.050125", "bytes_sent": 15073280, "upload": 11855583.997354422, "server": {"latency": 22.216, "name": "Manassas, VA", "url": "http://stosat-rstn-01.sys.comcast.net/speedtest/upload.php", "country": "United States", "lon": "-77.4764", "cc": "US", "host": "stosat-rstn-01.sys.comcast.net:8080", "sponsor": "Comcast", "url2": "http://a-stosat-rstn-01.sys.comcast.net/speedtest/upload.php", "lat": "38.7514", "id": "9839", "d": 30.88789265402574}, "download": 93467604.32673639, "ping": 22.216},{"bytes_received": 117102462, "timestamp": "2017-06-29T15:00:01.055618", "bytes_sent": 14131200, "upload": 8341734.150507023, "server": {"latency": 21.338, "name": "Manassas, VA", "url": "http://stosat-rstn-01.sys.comcast.net/speedtest/upload.php", "country": "United States", "lon": "-77.4764", "cc": "US", "host": "stosat-rstn-01.sys.comcast.net:8080", "sponsor": "Comcast", "url2": "http://a-stosat-rstn-01.sys.comcast.net/speedtest/upload.php", "lat": "38.7514", "id": "9839", "d": 30.88789265402574}, "download": 93180044.59277852, "ping": 21.338},{"bytes_received": 116494854, "timestamp": "2017-06-29T15:15:01.095767", "bytes_sent": 14123008, "upload": 8304829.995043559, "server": {"latency": 21.633, "name": "Manassas, VA", "url": "http://stosat-rstn-01.sys.comcast.net/speedtest/upload.php", "country": "United States", "lon": "-77.4764", "cc": "US", "host": "stosat-rstn-01.sys.comcast.net:8080", "sponsor": "Comcast", "url2": "http://a-stosat-rstn-01.sys.comcast.net/speedtest/upload.php", "lat": "38.7514", "id": "9839", "d": 30.88789265402574}, "download": 92915650.06161056, "ping": 21.633},{"bytes_received": 117160454, "timestamp": "2017-06-29T15:30:01.101774", "bytes_sent": 14172160, "upload": 11071127.439008417, "server": {"latency": 23.396, "name": "Manassas, VA", "url": "http://stosat-rstn-01.sys.comcast.net/speedtest/upload.php", "country": "United States", "lon": "-77.4764", "cc": "US", "host": "stosat-rstn-01.sys.comcast.net:8080", "sponsor": "Comcast", "url2": "http://a-stosat-rstn-01.sys.comcast.net/speedtest/upload.php", "lat": "38.7514", "id": "9839", "d": 30.88789265402574}, "download": 93449769.83457191, "ping": 23.396},{"bytes_received": 117143422, "timestamp": "2017-06-29T15:45:01.872745", "bytes_sent": 13844480, "upload": 10889130.374411406, "server": {"latency": 22.643, "name": "Manassas, VA", "url": "http://stosat-rstn-01.sys.comcast.net/speedtest/upload.php", "country": "United States", "lon": "-77.4764", "cc": "US", "host": "stosat-rstn-01.sys.comcast.net:8080", "sponsor": "Comcast", "url2": "http://a-stosat-rstn-01.sys.comcast.net/speedtest/upload.php", "lat": "38.7514", "id": "9839", "d": 30.88789265402574}, "download": 93421141.62357312, "ping": 22.643},{"bytes_received": 115430388, "timestamp": "2017-06-29T16:00:01.059371", "bytes_sent": 15007744, "upload": 11896868.801073963, "server": {"latency": 33.938, "name": "Reston, VA", "url": "http://speed1.iad2.inforelay.net/speedtest/upload.php", "country": "United States", "lon": "-77.3414", "cc": "US", "host": "speed1.iad2.inforelay.net:8080", "sponsor": "InfoRelay Online Systems", "url2": "http://67.208.74.124/speedtest/upload.php", "lat": "38.9686", "id": "1344", "d": 25.39058718521606}, "download": 91498616.00184509, "ping": 33.938},{"bytes_received": 117218056, "timestamp": "2017-06-29T16:15:01.087968", "bytes_sent": 14794752, "upload": 11740163.985986426, "server": {"latency": 19.802, "name": "Manassas, VA", "url": "http://stosat-rstn-01.sys.comcast.net/speedtest/upload.php", "country": "United States", "lon": "-77.4764", "cc": "US", "host": "stosat-rstn-01.sys.comcast.net:8080", "sponsor": "Comcast", "url2": "http://a-stosat-rstn-01.sys.comcast.net/speedtest/upload.php", "lat": "38.7514", "id": "9839", "d": 30.88789265402574}, "download": 93246632.41472441, "ping": 19.802},{"bytes_received": 117235582, "timestamp": "2017-06-29T16:30:01.040989", "bytes_sent": 14917632, "upload": 11837977.68888395, "server": {"latency": 21.428, "name": "Manassas, VA", "url": "http://stosat-rstn-01.sys.comcast.net/speedtest/upload.php", "country": "United States", "lon": "-77.4764", "cc": "US", "host": "stosat-rstn-01.sys.comcast.net:8080", "sponsor": "Comcast", "url2": "http://a-stosat-rstn-01.sys.comcast.net/speedtest/upload.php", "lat": "38.7514", "id": "9839", "d": 30.88789265402574}, "download": 93441760.30758752, "ping": 21.428},{"bytes_received": 117156616, "timestamp": "2017-06-29T16:45:01.138795", "bytes_sent": 15065088, "upload": 11821508.504228985, "server": {"latency": 21.38, "name": "Manassas, VA", "url": "http://stosat-rstn-01.sys.comcast.net/speedtest/upload.php", "country": "United States", "lon": "-77.4764", "cc": "US", "host": "stosat-rstn-01.sys.comcast.net:8080", "sponsor": "Comcast", "url2": "http://a-stosat-rstn-01.sys.comcast.net/speedtest/upload.php", "lat": "38.7514", "id": "9839", "d": 30.88789265402574}, "download": 93349513.68172318, "ping": 21.38},{"bytes_received": 117207322, "timestamp": "2017-06-29T17:00:01.058027", "bytes_sent": 15073280, "upload": 11906117.238338258, "server": {"latency": 18.996, "name": "Manassas, VA", "url": "http://stosat-rstn-01.sys.comcast.net/speedtest/upload.php", "country": "United States", "lon": "-77.4764", "cc": "US", "host": "stosat-rstn-01.sys.comcast.net:8080", "sponsor": "Comcast", "url2": "http://a-stosat-rstn-01.sys.comcast.net/speedtest/upload.php", "lat": "38.7514", "id": "9839", "d": 30.88789265402574}, "download": 93278522.65180038, "ping": 18.996},{"bytes_received": 117168234, "timestamp": "2017-06-29T17:15:01.052322", "bytes_sent": 15040512, "upload": 11896767.350680266, "server": {"latency": 23.222, "name": "Manassas, VA", "url": "http://stosat-rstn-01.sys.comcast.net/speedtest/upload.php", "country": "United States", "lon": "-77.4764", "cc": "US", "host": "stosat-rstn-01.sys.comcast.net:8080", "sponsor": "Comcast", "url2": "http://a-stosat-rstn-01.sys.comcast.net/speedtest/upload.php", "lat": "38.7514", "id": "9839", "d": 30.88789265402574}, "download": 93132308.64173144, "ping": 23.222},{"bytes_received": 117215102, "timestamp": "2017-06-29T17:30:01.070037", "bytes_sent": 15073280, "upload": 11811670.405194137, "server": {"latency": 22.155, "name": "Manassas, VA", "url": "http://stosat-rstn-01.sys.comcast.net/speedtest/upload.php", "country": "United States", "lon": "-77.4764", "cc": "US", "host": "stosat-rstn-01.sys.comcast.net:8080", "sponsor": "Comcast", "url2": "http://a-stosat-rstn-01.sys.comcast.net/speedtest/upload.php", "lat": "38.7514", "id": "9839", "d": 30.88789265402574}, "download": 93274750.17077619, "ping": 22.155},{"bytes_received": 117235582, "timestamp": "2017-06-29T17:45:01.017087", "bytes_sent": 14958592, "upload": 11855346.728934327, "server": {"latency": 21.398, "name": "Manassas, VA", "url": "http://stosat-rstn-01.sys.comcast.net/speedtest/upload.php", "country": "United States", "lon": "-77.4764", "cc": "US", "host": "stosat-rstn-01.sys.comcast.net:8080", "sponsor": "Comcast", "url2": "http://a-stosat-rstn-01.sys.comcast.net/speedtest/upload.php", "lat": "38.7514", "id": "9839", "d": 30.88789265402574}, "download": 93360425.49648345, "ping": 21.398},{"bytes_received": 117235582, "timestamp": "2017-06-29T18:00:01.055845", "bytes_sent": 15024128, "upload": 9689622.54818807, "server": {"latency": 17.858, "name": "Manassas, VA", "url": "http://stosat-rstn-01.sys.comcast.net/speedtest/upload.php", "country": "United States", "lon": "-77.4764", "cc": "US", "host": "stosat-rstn-01.sys.comcast.net:8080", "sponsor": "Comcast", "url2": "http://a-stosat-rstn-01.sys.comcast.net/speedtest/upload.php", "lat": "38.7514", "id": "9839", "d": 30.88789265402574}, "download": 93446592.60410094, "ping": 17.858},{"bytes_received": 117230662, "timestamp": "2017-06-29T18:15:01.068507", "bytes_sent": 14876672, "upload": 11811152.44219699, "server": {"latency": 21.488, "name": "Manassas, VA", "url": "http://stosat-rstn-01.sys.comcast.net/speedtest/upload.php", "country": "United States", "lon": "-77.4764", "cc": "US", "host": "stosat-rstn-01.sys.comcast.net:8080", "sponsor": "Comcast", "url2": "http://a-stosat-rstn-01.sys.comcast.net/speedtest/upload.php", "lat": "38.7514", "id": "9839", "d": 30.88789265402574}, "download": 93488555.23134421, "ping": 21.488},{"bytes_received": 117018082, "timestamp": "2017-06-29T18:30:01.087627", "bytes_sent": 15138816, "upload": 11909997.70328284, "server": {"latency": 20.77, "name": "Manassas, VA", "url": "http://stosat-rstn-01.sys.comcast.net/speedtest/upload.php", "country": "United States", "lon": "-77.4764", "cc": "US", "host": "stosat-rstn-01.sys.comcast.net:8080", "sponsor": "Comcast", "url2": "http://a-stosat-rstn-01.sys.comcast.net/speedtest/upload.php", "lat": "38.7514", "id": "9839", "d": 30.88789265402574}, "download": 93094430.83485791, "ping": 20.77},{"bytes_received": 117171682, "timestamp": "2017-06-29T18:45:01.091076", "bytes_sent": 14966784, "upload": 11890864.259268144, "server": {"latency": 20.405, "name": "Manassas, VA", "url": "http://stosat-rstn-01.sys.comcast.net/speedtest/upload.php", "country": "United States", "lon": "-77.4764", "cc": "US", "host": "stosat-rstn-01.sys.comcast.net:8080", "sponsor": "Comcast", "url2": "http://a-stosat-rstn-01.sys.comcast.net/speedtest/upload.php", "lat": "38.7514", "id": "9839", "d": 30.88789265402574}, "download": 93375021.56460147, "ping": 20.405},{"bytes_received": 117214608, "timestamp": "2017-06-29T19:00:01.173905", "bytes_sent": 15056896, "upload": 11769806.751125554, "server": {"latency": 22.055, "name": "Manassas, VA", "url": "http://stosat-rstn-01.sys.comcast.net/speedtest/upload.php", "country": "United States", "lon": "-77.4764", "cc": "US", "host": "stosat-rstn-01.sys.comcast.net:8080", "sponsor": "Comcast", "url2": "http://a-stosat-rstn-01.sys.comcast.net/speedtest/upload.php", "lat": "38.7514", "id": "9839", "d": 30.88789265402574}, "download": 93392631.97988416, "ping": 22.055},{"bytes_received": 117201908, "timestamp": "2017-06-29T19:15:01.051930", "bytes_sent": 14934016, "upload": 11646059.586281998, "server": {"latency": 23.07, "name": "Manassas, VA", "url": "http://stosat-rstn-01.sys.comcast.net/speedtest/upload.php", "country": "United States", "lon": "-77.4764", "cc": "US", "host": "stosat-rstn-01.sys.comcast.net:8080", "sponsor": "Comcast", "url2": "http://a-stosat-rstn-01.sys.comcast.net/speedtest/upload.php", "lat": "38.7514", "id": "9839", "d": 30.88789265402574}, "download": 93397629.3816646, "ping": 23.07},{"bytes_received": 117230168, "timestamp": "2017-06-29T19:30:01.088895", "bytes_sent": 14991360, "upload": 11848730.134256924, "server": {"latency": 22.123, "name": "Manassas, VA", "url": "http://stosat-rstn-01.sys.comcast.net/speedtest/upload.php", "country": "United States", "lon": "-77.4764", "cc": "US", "host": "stosat-rstn-01.sys.comcast.net:8080", "sponsor": "Comcast", "url2": "http://a-stosat-rstn-01.sys.comcast.net/speedtest/upload.php", "lat": "38.7514", "id": "9839", "d": 30.88789265402574}, "download": 93447769.09383306, "ping": 22.123},{"bytes_received": 117157994, "timestamp": "2017-06-29T19:45:01.101491", "bytes_sent": 15056896, "upload": 10147547.812485145, "server": {"latency": 22.317, "name": "Manassas, VA", "url": "http://stosat-rstn-01.sys.comcast.net/speedtest/upload.php", "country": "United States", "lon": "-77.4764", "cc": "US", "host": "stosat-rstn-01.sys.comcast.net:8080", "sponsor": "Comcast", "url2": "http://a-stosat-rstn-01.sys.comcast.net/speedtest/upload.php", "lat": "38.7514", "id": "9839", "d": 30.88789265402574}, "download": 92925868.2881433, "ping": 22.317},{"bytes_received": 117002522, "timestamp": "2017-06-29T20:00:01.060460", "bytes_sent": 15065088, "upload": 11944683.12214813, "server": {"latency": 18.737, "name": "Manassas, VA", "url": "http://stosat-rstn-01.sys.comcast.net/speedtest/upload.php", "country": "United States", "lon": "-77.4764", "cc": "US", "host": "stosat-rstn-01.sys.comcast.net:8080", "sponsor": "Comcast", "url2": "http://a-stosat-rstn-01.sys.comcast.net/speedtest/upload.php", "lat": "38.7514", "id": "9839", "d": 30.88789265402574}, "download": 93259102.89605522, "ping": 18.737},{"bytes_received": 117178968, "timestamp": "2017-06-29T20:15:01.054786", "bytes_sent": 15024128, "upload": 11898718.451712832, "server": {"latency": 19.722, "name": "Manassas, VA", "url": "http://stosat-rstn-01.sys.comcast.net/speedtest/upload.php", "country": "United States", "lon": "-77.4764", "cc": "US", "host": "stosat-rstn-01.sys.comcast.net:8080", "sponsor": "Comcast", "url2": "http://a-stosat-rstn-01.sys.comcast.net/speedtest/upload.php", "lat": "38.7514", "id": "9839", "d": 30.88789265402574}, "download": 93303064.55562516, "ping": 19.722},{"bytes_received": 117153662, "timestamp": "2017-06-29T20:30:01.061954", "bytes_sent": 15138816, "upload": 11944822.764042389, "server": {"latency": 20.211, "name": "Manassas, VA", "url": "http://stosat-rstn-01.sys.comcast.net/speedtest/upload.php", "country": "United States", "lon": "-77.4764", "cc": "US", "host": "stosat-rstn-01.sys.comcast.net:8080", "sponsor": "Comcast", "url2": "http://a-stosat-rstn-01.sys.comcast.net/speedtest/upload.php", "lat": "38.7514", "id": "9839", "d": 30.88789265402574}, "download": 93310588.53807965, "ping": 20.211},{"bytes_received": 117156122, "timestamp": "2017-06-29T20:45:01.047495", "bytes_sent": 14909440, "upload": 11829660.335536975, "server": {"latency": 19.823, "name": "Manassas, VA", "url": "http://stosat-rstn-01.sys.comcast.net/speedtest/upload.php", "country": "United States", "lon": "-77.4764", "cc": "US", "host": "stosat-rstn-01.sys.comcast.net:8080", "sponsor": "Comcast", "url2": "http://a-stosat-rstn-01.sys.comcast.net/speedtest/upload.php", "lat": "38.7514", "id": "9839", "d": 30.88789265402574}, "download": 93327731.66239472, "ping": 19.823},{"bytes_received": 117184382, "timestamp": "2017-06-29T21:00:01.094853", "bytes_sent": 15114240, "upload": 11783978.59786917, "server": {"latency": 20.654, "name": "Manassas, VA", "url": "http://stosat-rstn-01.sys.comcast.net/speedtest/upload.php", "country": "United States", "lon": "-77.4764", "cc": "US", "host": "stosat-rstn-01.sys.comcast.net:8080", "sponsor": "Comcast", "url2": "http://a-stosat-rstn-01.sys.comcast.net/speedtest/upload.php", "lat": "38.7514", "id": "9839", "d": 30.88789265402574}, "download": 93364245.7700092, "ping": 20.654},{"bytes_received": 117214608, "timestamp": "2017-06-29T21:15:01.070980", "bytes_sent": 15138816, "upload": 11918498.603365673, "server": {"latency": 20.021, "name": "Manassas, VA", "url": "http://stosat-rstn-01.sys.comcast.net/speedtest/upload.php", "country": "United States", "lon": "-77.4764", "cc": "US", "host": "stosat-rstn-01.sys.comcast.net:8080", "sponsor": "Comcast", "url2": "http://a-stosat-rstn-01.sys.comcast.net/speedtest/upload.php", "lat": "38.7514", "id": "9839", "d": 30.88789265402574}, "download": 92988979.46513525, "ping": 20.021},{"bytes_received": 117171188, "timestamp": "2017-06-29T21:30:01.054164", "bytes_sent": 15089664, "upload": 11963759.394165415, "server": {"latency": 19.671, "name": "Manassas, VA", "url": "http://stosat-rstn-01.sys.comcast.net/speedtest/upload.php", "country": "United States", "lon": "-77.4764", "cc": "US", "host": "stosat-rstn-01.sys.comcast.net:8080", "sponsor": "Comcast", "url2": "http://a-stosat-rstn-01.sys.comcast.net/speedtest/upload.php", "lat": "38.7514", "id": "9839", "d": 30.88789265402574}, "download": 93232126.35803625, "ping": 19.671},{"bytes_received": 117219928, "timestamp": "2017-06-29T21:45:01.112996", "bytes_sent": 15040512, "upload": 9870500.483548284, "server": {"latency": 23.357, "name": "Manassas, VA", "url": "http://stosat-rstn-01.sys.comcast.net/speedtest/upload.php", "country": "United States", "lon": "-77.4764", "cc": "US", "host": "stosat-rstn-01.sys.comcast.net:8080", "sponsor": "Comcast", "url2": "http://a-stosat-rstn-01.sys.comcast.net/speedtest/upload.php", "lat": "38.7514", "id": "9839", "d": 30.88789265402574}, "download": 93220034.32453965, "ping": 23.357},{"bytes_received": 117151202, "timestamp": "2017-06-29T22:00:01.052635", "bytes_sent": 14868480, "upload": 11813826.285732526, "server": {"latency": 22.159, "name": "Manassas, VA", "url": "http://stosat-rstn-01.sys.comcast.net/speedtest/upload.php", "country": "United States", "lon": "-77.4764", "cc": "US", "host": "stosat-rstn-01.sys.comcast.net:8080", "sponsor": "Comcast", "url2": "http://a-stosat-rstn-01.sys.comcast.net/speedtest/upload.php", "lat": "38.7514", "id": "9839", "d": 30.88789265402574}, "download": 93149517.18472236, "ping": 22.159},{"bytes_received": 116352482, "timestamp": "2017-06-29T22:15:01.058311", "bytes_sent": 14983168, "upload": 11878193.24867211, "server": {"latency": 29.975, "name": "Washington, DC", "url": "http://sp1.aethosting.com/upload.php", "country": "United States", "lon": "-77.0164", "cc": "US", "host": "speedtest.aethosting.com:8080", "sponsor": "AET Hosting Solutions", "url2": "http://sp2.aethosting.com/upload.php", "lat": "38.9047", "id": "7960", "d": 14.199124910496671}, "download": 92599606.20266388, "ping": 29.975},{"bytes_received": 117156122, "timestamp": "2017-06-29T22:30:01.287800", "bytes_sent": 14958592, "upload": 11821296.736936133, "server": {"latency": 21.036, "name": "Manassas, VA", "url": "http://stosat-rstn-01.sys.comcast.net/speedtest/upload.php", "country": "United States", "lon": "-77.4764", "cc": "US", "host": "stosat-rstn-01.sys.comcast.net:8080", "sponsor": "Comcast", "url2": "http://a-stosat-rstn-01.sys.comcast.net/speedtest/upload.php", "lat": "38.7514", "id": "9839", "d": 30.88789265402574}, "download": 93220434.68641649, "ping": 21.036},{"bytes_received": 103849936, "timestamp": "2017-06-29T22:45:01.111091", "bytes_sent": 15040512, "upload": 11921298.30569581, "server": {"latency": 22.212, "name": "Manassas, VA", "url": "http://stosat-rstn-01.sys.comcast.net/speedtest/upload.php", "country": "United States", "lon": "-77.4764", "cc": "US", "host": "stosat-rstn-01.sys.comcast.net:8080", "sponsor": "Comcast", "url2": "http://a-stosat-rstn-01.sys.comcast.net/speedtest/upload.php", "lat": "38.7514", "id": "9839", "d": 30.88789265402574}, "download": 82752003.13936536, "ping": 22.212},{"bytes_received": 117256062, "timestamp": "2017-06-29T23:00:01.047200", "bytes_sent": 14983168, "upload": 11943210.227671765, "server": {"latency": 18.08, "name": "Manassas, VA", "url": "http://stosat-rstn-01.sys.comcast.net/speedtest/upload.php", "country": "United States", "lon": "-77.4764", "cc": "US", "host": "stosat-rstn-01.sys.comcast.net:8080", "sponsor": "Comcast", "url2": "http://a-stosat-rstn-01.sys.comcast.net/speedtest/upload.php", "lat": "38.7514", "id": "9839", "d": 30.88789265402574}, "download": 92988835.2712394, "ping": 18.08},{"bytes_received": 117140468, "timestamp": "2017-06-29T23:15:01.088647", "bytes_sent": 15097856, "upload": 11801271.301610896, "server": {"latency": 20.599, "name": "Manassas, VA", "url": "http://stosat-rstn-01.sys.comcast.net/speedtest/upload.php", "country": "United States", "lon": "-77.4764", "cc": "US", "host": "stosat-rstn-01.sys.comcast.net:8080", "sponsor": "Comcast", "url2": "http://a-stosat-rstn-01.sys.comcast.net/speedtest/upload.php", "lat": "38.7514", "id": "9839", "d": 30.88789265402574}, "download": 93355084.49116306, "ping": 20.599},{"bytes_received": 116990316, "timestamp": "2017-06-29T23:30:01.069194", "bytes_sent": 15089664, "upload": 11932685.37698577, "server": {"latency": 20.371, "name": "Manassas, VA", "url": "http://stosat-rstn-01.sys.comcast.net/speedtest/upload.php", "country": "United States", "lon": "-77.4764", "cc": "US", "host": "stosat-rstn-01.sys.comcast.net:8080", "sponsor": "Comcast", "url2": "http://a-stosat-rstn-01.sys.comcast.net/speedtest/upload.php", "lat": "38.7514", "id": "9839", "d": 30.88789265402574}, "download": 92740157.67188507, "ping": 20.371},{"bytes_received": 115006216, "timestamp": "2017-06-29T23:45:01.046813", "bytes_sent": 15007744, "upload": 8681205.119652282, "server": {"latency": 28.914, "name": "Washington, DC", "url": "http://sp1.aethosting.com/upload.php", "country": "United States", "lon": "-77.0164", "cc": "US", "host": "speedtest.aethosting.com:8080", "sponsor": "AET Hosting Solutions", "url2": "http://sp2.aethosting.com/upload.php", "lat": "38.9047", "id": "7960", "d": 14.199124910496671}, "download": 91187766.56895968, "ping": 28.914},{"bytes_received": 117181428, "timestamp": "2017-06-30T00:00:01.101292", "bytes_sent": 14712832, "upload": 11715727.450530717, "server": {"latency": 21.401, "name": "Manassas, VA", "url": "http://stosat-rstn-01.sys.comcast.net/speedtest/upload.php", "country": "United States", "lon": "-77.4764", "cc": "US", "host": "stosat-rstn-01.sys.comcast.net:8080", "sponsor": "Comcast", "url2": "http://a-stosat-rstn-01.sys.comcast.net/speedtest/upload.php", "lat": "38.7514", "id": "9839", "d": 30.88789265402574}, "download": 93190426.26677929, "ping": 21.401},{"bytes_received": 117171682, "timestamp": "2017-06-30T00:15:01.065040", "bytes_sent": 15089664, "upload": 11886912.181740021, "server": {"latency": 20.355, "name": "Manassas, VA", "url": "http://stosat-rstn-01.sys.comcast.net/speedtest/upload.php", "country": "United States", "lon": "-77.4764", "cc": "US", "host": "stosat-rstn-01.sys.comcast.net:8080", "sponsor": "Comcast", "url2": "http://a-stosat-rstn-01.sys.comcast.net/speedtest/upload.php", "lat": "38.7514", "id": "9839", "d": 30.88789265402574}, "download": 93183574.4716026, "ping": 20.355},{"bytes_received": 117163902, "timestamp": "2017-06-30T00:30:01.049402", "bytes_sent": 13484032, "upload": 10635862.432878949, "server": {"latency": 25.422, "name": "Manassas, VA", "url": "http://stosat-rstn-01.sys.comcast.net/speedtest/upload.php", "country": "United States", "lon": "-77.4764", "cc": "US", "host": "stosat-rstn-01.sys.comcast.net:8080", "sponsor": "Comcast", "url2": "http://a-stosat-rstn-01.sys.comcast.net/speedtest/upload.php", "lat": "38.7514", "id": "9839", "d": 30.88789265402574}, "download": 93229231.71305141, "ping": 25.422},{"bytes_received": 117038562, "timestamp": "2017-06-30T00:45:01.058473", "bytes_sent": 14958592, "upload": 11899700.771014566, "server": {"latency": 21.63, "name": "Manassas, VA", "url": "http://stosat-rstn-01.sys.comcast.net/speedtest/upload.php", "country": "United States", "lon": "-77.4764", "cc": "US", "host": "stosat-rstn-01.sys.comcast.net:8080", "sponsor": "Comcast", "url2": "http://a-stosat-rstn-01.sys.comcast.net/speedtest/upload.php", "lat": "38.7514", "id": "9839", "d": 30.88789265402574}, "download": 93276668.57757051, "ping": 21.63}]}
