{"speedlogs":[
{"bytes_received": 117112702, "timestamp": "2017-10-13T04:00:08.831283", "bytes_sent": 14950400, "upload": 11727959.928139584, "server": {"latency": 20.667, "name": "Washington, DC", "url": "http://was.speedtest.sbcglobal.net/speedtest/upload.php", "country": "United States", "lon": "-77.0164", "cc": "US", "host": "was.speedtest.sbcglobal.net:8080", "sponsor": "AT&T", "lat": "38.9047", "id": "5113", "d": 14.199124910496671}, "download": 93367845.49974597, "ping": 20.667},{"bytes_received": 116992282, "timestamp": "2017-10-13T04:15:01.195410", "bytes_sent": 14999552, "upload": 11785495.50418392, "server": {"latency": 19.172, "name": "Washington, DC", "url": "http://was.speedtest.sbcglobal.net/speedtest/upload.php", "country": "United States", "lon": "-77.0164", "cc": "US", "host": "was.speedtest.sbcglobal.net:8080", "sponsor": "AT&T", "lat": "38.9047", "id": "5113", "d": 14.199124910496671}, "download": 93281564.0661981, "ping": 19.172},{"bytes_received": 117163902, "timestamp": "2017-10-13T04:30:01.291538", "bytes_sent": 15048704, "upload": 11904075.729950266, "server": {"latency": 20.922, "name": "Fairfax, VA", "url": "http://speedtest.rdc.dc.cox.net/speedtest/upload.php", "country": "United States", "lon": "-77.3063", "cc": "US", "host": "speedtest.rd.dc.cox.net:8080", "sponsor": "CCI - Nova", "lat": "38.8462", "id": "14122", "d": 15.87758843134814}, "download": 93453333.09673853, "ping": 20.922},{"bytes_received": 117159076, "timestamp": "2017-10-13T04:45:01.391765", "bytes_sent": 14835712, "upload": 11833936.261309909, "server": {"latency": 20.814, "name": "Fairfax, VA", "url": "http://speedtest.rdc.dc.cox.net/speedtest/upload.php", "country": "United States", "lon": "-77.3063", "cc": "US", "host": "speedtest.rd.dc.cox.net:8080", "sponsor": "CCI - Nova", "lat": "38.8462", "id": "14122", "d": 15.87758843134814}, "download": 93216593.571196, "ping": 20.814},{"bytes_received": 117043976, "timestamp": "2017-10-13T05:00:01.396762", "bytes_sent": 14917632, "upload": 11708415.313908625, "server": {"latency": 20.507, "name": "Washington, DC", "url": "http://was.speedtest.sbcglobal.net/speedtest/upload.php", "country": "United States", "lon": "-77.0164", "cc": "US", "host": "was.speedtest.sbcglobal.net:8080", "sponsor": "AT&T", "lat": "38.9047", "id": "5113", "d": 14.199124910496671}, "download": 93275232.1048642, "ping": 20.507},{"bytes_received": 115295396, "timestamp": "2017-10-13T05:15:01.130027", "bytes_sent": 11231232, "upload": 8832100.264548087, "server": {"latency": 19.186, "name": "Washington, DC", "url": "http://was.speedtest.sbcglobal.net/speedtest/upload.php", "country": "United States", "lon": "-77.0164", "cc": "US", "host": "was.speedtest.sbcglobal.net:8080", "sponsor": "AT&T", "lat": "38.9047", "id": "5113", "d": 14.199124910496671}, "download": 91988242.8852519, "ping": 19.186},{"bytes_received": 117110242, "timestamp": "2017-10-13T05:30:01.220380", "bytes_sent": 15163392, "upload": 11897618.031729896, "server": {"latency": 21.25, "name": "Reston, VA", "url": "http://speed1.iad2.inforelay.net/speedtest/upload.php", "country": "United States", "lon": "-77.3414", "cc": "US", "host": "speed1.iad2.inforelay.net:8080", "sponsor": "InfoRelay Online Systems", "url2": "http://67.208.74.124/speedtest/upload.php", "lat": "38.9686", "id": "1344", "d": 25.39058718521606}, "download": 93393826.1954666, "ping": 21.25},{"bytes_received": 117146376, "timestamp": "2017-10-13T05:45:02.196143", "bytes_sent": 15081472, "upload": 9523115.174596025, "server": {"latency": 20.921, "name": "Fairfax, VA", "url": "http://speedtest.rdc.dc.cox.net/speedtest/upload.php", "country": "United States", "lon": "-77.3063", "cc": "US", "host": "speedtest.rd.dc.cox.net:8080", "sponsor": "CCI - Nova", "lat": "38.8462", "id": "14122", "d": 15.87758843134814}, "download": 93212662.16853693, "ping": 20.921},{"bytes_received": 117228296, "timestamp": "2017-10-13T06:00:01.354680", "bytes_sent": 15024128, "upload": 11889572.863669645, "server": {"latency": 20.091, "name": "Reston, VA", "url": "http://speed1.iad2.inforelay.net/speedtest/upload.php", "country": "United States", "lon": "-77.3414", "cc": "US", "host": "speed1.iad2.inforelay.net:8080", "sponsor": "InfoRelay Online Systems", "url2": "http://67.208.74.124/speedtest/upload.php", "lat": "38.9686", "id": "1344", "d": 25.39058718521606}, "download": 93240852.01264529, "ping": 20.091},{"bytes_received": 117143422, "timestamp": "2017-10-13T06:15:01.245118", "bytes_sent": 12951552, "upload": 10244937.983928123, "server": {"latency": 19.788, "name": "Washington, DC", "url": "http://was.speedtest.sbcglobal.net/speedtest/upload.php", "country": "United States", "lon": "-77.0164", "cc": "US", "host": "was.speedtest.sbcglobal.net:8080", "sponsor": "AT&T", "lat": "38.9047", "id": "5113", "d": 14.199124910496671}, "download": 93287806.67019716, "ping": 19.788},{"bytes_received": 117002522, "timestamp": "2017-10-13T06:30:01.353710", "bytes_sent": 14966784, "upload": 11747483.230408076, "server": {"latency": 19.753, "name": "Washington, DC", "url": "http://was.speedtest.sbcglobal.net/speedtest/upload.php", "country": "United States", "lon": "-77.0164", "cc": "US", "host": "was.speedtest.sbcglobal.net:8080", "sponsor": "AT&T", "lat": "38.9047", "id": "5113", "d": 14.199124910496671}, "download": 92770865.05155306, "ping": 19.753},{"bytes_received": 116542216, "timestamp": "2017-10-13T06:45:01.291052", "bytes_sent": 15073280, "upload": 11900222.354821034, "server": {"latency": 20.306, "name": "Washington, DC", "url": "http://was.speedtest.sbcglobal.net/speedtest/upload.php", "country": "United States", "lon": "-77.0164", "cc": "US", "host": "was.speedtest.sbcglobal.net:8080", "sponsor": "AT&T", "lat": "38.9047", "id": "5113", "d": 14.199124910496671}, "download": 92854776.10839452, "ping": 20.306},{"bytes_received": 117225342, "timestamp": "2017-10-13T07:00:01.334105", "bytes_sent": 15040512, "upload": 11853009.472156107, "server": {"latency": 21.035, "name": "Reston, VA", "url": "http://speed1.iad2.inforelay.net/speedtest/upload.php", "country": "United States", "lon": "-77.3414", "cc": "US", "host": "speed1.iad2.inforelay.net:8080", "sponsor": "InfoRelay Online Systems", "url2": "http://67.208.74.124/speedtest/upload.php", "lat": "38.9686", "id": "1344", "d": 25.39058718521606}, "download": 93367330.08025186, "ping": 21.035},{"bytes_received": 117191668, "timestamp": "2017-10-13T07:15:01.352765", "bytes_sent": 15015936, "upload": 11882135.520834768, "server": {"latency": 20.53, "name": "Fairfax, VA", "url": "http://speedtest.rdc.dc.cox.net/speedtest/upload.php", "country": "United States", "lon": "-77.3063", "cc": "US", "host": "speedtest.rd.dc.cox.net:8080", "sponsor": "CCI - Nova", "lat": "38.8462", "id": "14122", "d": 15.87758843134814}, "download": 93226160.22625619, "ping": 20.53},{"bytes_received": 116405648, "timestamp": "2017-10-13T07:30:07.296262", "bytes_sent": 15130624, "upload": 11952778.874961236, "server": {"latency": 21.539, "name": "Fairfax, VA", "url": "http://speedtest.rdc.dc.cox.net/speedtest/upload.php", "country": "United States", "lon": "-77.3063", "cc": "US", "host": "speedtest.rd.dc.cox.net:8080", "sponsor": "CCI - Nova", "lat": "38.8462", "id": "14122", "d": 15.87758843134814}, "download": 92796519.53263721, "ping": 21.539},{"bytes_received": 117135642, "timestamp": "2017-10-13T07:45:01.203037", "bytes_sent": 15147008, "upload": 11882223.135538645, "server": {"latency": 21.846, "name": "Fairfax, VA", "url": "http://speedtest.rdc.dc.cox.net/speedtest/upload.php", "country": "United States", "lon": "-77.3063", "cc": "US", "host": "speedtest.rd.dc.cox.net:8080", "sponsor": "CCI - Nova", "lat": "38.8462", "id": "14122", "d": 15.87758843134814}, "download": 93190413.34483896, "ping": 21.846},{"bytes_received": 117125402, "timestamp": "2017-10-13T08:00:02.653839", "bytes_sent": 15106048, "upload": 11924440.429342927, "server": {"latency": 19.78, "name": "Washington, DC", "url": "http://was.speedtest.sbcglobal.net/speedtest/upload.php", "country": "United States", "lon": "-77.0164", "cc": "US", "host": "was.speedtest.sbcglobal.net:8080", "sponsor": "AT&T", "lat": "38.9047", "id": "5113", "d": 14.199124910496671}, "download": 92852226.47001745, "ping": 19.78},{"bytes_received": 117125402, "timestamp": "2017-10-13T08:15:01.155228", "bytes_sent": 15138816, "upload": 11912177.590086916, "server": {"latency": 19.98, "name": "Washington, DC", "url": "http://was.speedtest.sbcglobal.net/speedtest/upload.php", "country": "United States", "lon": "-77.0164", "cc": "US", "host": "was.speedtest.sbcglobal.net:8080", "sponsor": "AT&T", "lat": "38.9047", "id": "5113", "d": 14.199124910496671}, "download": 93155889.98511772, "ping": 19.98},{"bytes_received": 113705736, "timestamp": "2017-10-13T08:30:01.486062", "bytes_sent": 14991360, "upload": 11804199.597568924, "server": {"latency": 21.496, "name": "Fairfax, VA", "url": "http://speedtest.rdc.dc.cox.net/speedtest/upload.php", "country": "United States", "lon": "-77.3063", "cc": "US", "host": "speedtest.rd.dc.cox.net:8080", "sponsor": "CCI - Nova", "lat": "38.8462", "id": "14122", "d": 15.87758843134814}, "download": 90662422.08424504, "ping": 21.496},{"bytes_received": 117181922, "timestamp": "2017-10-13T08:45:01.378314", "bytes_sent": 14934016, "upload": 11837257.614281178, "server": {"latency": 21.097, "name": "Fairfax, VA", "url": "http://speedtest.rdc.dc.cox.net/speedtest/upload.php", "country": "United States", "lon": "-77.3063", "cc": "US", "host": "speedtest.rd.dc.cox.net:8080", "sponsor": "CCI - Nova", "lat": "38.8462", "id": "14122", "d": 15.87758843134814}, "download": 92916509.48209378, "ping": 21.097},{"bytes_received": 117046436, "timestamp": "2017-10-13T09:00:01.482056", "bytes_sent": 15056896, "upload": 11869951.880568959, "server": {"latency": 19.493, "name": "Washington, DC", "url": "http://was.speedtest.sbcglobal.net/speedtest/upload.php", "country": "United States", "lon": "-77.0164", "cc": "US", "host": "was.speedtest.sbcglobal.net:8080", "sponsor": "AT&T", "lat": "38.9047", "id": "5113", "d": 14.199124910496671}, "download": 93247560.53902185, "ping": 19.493},{"bytes_received": 117148836, "timestamp": "2017-10-13T09:15:01.221314", "bytes_sent": 15089664, "upload": 11859174.439802954, "server": {"latency": 19.31, "name": "Washington, DC", "url": "http://was.speedtest.sbcglobal.net/speedtest/upload.php", "country": "United States", "lon": "-77.0164", "cc": "US", "host": "was.speedtest.sbcglobal.net:8080", "sponsor": "AT&T", "lat": "38.9047", "id": "5113", "d": 14.199124910496671}, "download": 93162674.28833535, "ping": 19.31},{"bytes_received": 117184382, "timestamp": "2017-10-13T09:30:01.292248", "bytes_sent": 15056896, "upload": 11935121.79498616, "server": {"latency": 20.859, "name": "Reston, VA", "url": "http://speed1.iad2.inforelay.net/speedtest/upload.php", "country": "United States", "lon": "-77.3414", "cc": "US", "host": "speed1.iad2.inforelay.net:8080", "sponsor": "InfoRelay Online Systems", "url2": "http://67.208.74.124/speedtest/upload.php", "lat": "38.9686", "id": "1344", "d": 25.39058718521606}, "download": 93213568.7952919, "ping": 20.859},{"bytes_received": 117150708, "timestamp": "2017-10-13T09:45:01.305579", "bytes_sent": 14893056, "upload": 10564137.806894124, "server": {"latency": 20.921, "name": "Fairfax, VA", "url": "http://speedtest.rdc.dc.cox.net/speedtest/upload.php", "country": "United States", "lon": "-77.3063", "cc": "US", "host": "speedtest.rd.dc.cox.net:8080", "sponsor": "CCI - Nova", "lat": "38.8462", "id": "14122", "d": 15.87758843134814}, "download": 93498927.14042644, "ping": 20.921},{"bytes_received": 117036196, "timestamp": "2017-10-13T10:00:01.190239", "bytes_sent": 15081472, "upload": 11899236.69937646, "server": {"latency": 19.161, "name": "Washington, DC", "url": "http://was.speedtest.sbcglobal.net/speedtest/upload.php", "country": "United States", "lon": "-77.0164", "cc": "US", "host": "was.speedtest.sbcglobal.net:8080", "sponsor": "AT&T", "lat": "38.9047", "id": "5113", "d": 14.199124910496671}, "download": 93128658.56852618, "ping": 19.161},{"bytes_received": 117163902, "timestamp": "2017-10-13T10:15:01.185101", "bytes_sent": 15106048, "upload": 11892503.154103538, "server": {"latency": 21.399, "name": "Reston, VA", "url": "http://speed1.iad2.inforelay.net/speedtest/upload.php", "country": "United States", "lon": "-77.3414", "cc": "US", "host": "speed1.iad2.inforelay.net:8080", "sponsor": "InfoRelay Online Systems", "url2": "http://67.208.74.124/speedtest/upload.php", "lat": "38.9686", "id": "1344", "d": 25.39058718521606}, "download": 93287873.95213819, "ping": 21.399},{"bytes_received": 117104922, "timestamp": "2017-10-13T10:30:01.280880", "bytes_sent": 15122432, "upload": 11909845.300835727, "server": {"latency": 19.053, "name": "Washington, DC", "url": "http://was.speedtest.sbcglobal.net/speedtest/upload.php", "country": "United States", "lon": "-77.0164", "cc": "US", "host": "was.speedtest.sbcglobal.net:8080", "sponsor": "AT&T", "lat": "38.9047", "id": "5113", "d": 14.199124910496671}, "download": 93137435.46034323, "ping": 19.053},{"bytes_received": 117128262, "timestamp": "2017-10-13T10:45:01.154591", "bytes_sent": 14868480, "upload": 11668726.734558437, "server": {"latency": 21.193, "name": "Fairfax, VA", "url": "http://speedtest.rdc.dc.cox.net/speedtest/upload.php", "country": "United States", "lon": "-77.3063", "cc": "US", "host": "speedtest.rd.dc.cox.net:8080", "sponsor": "CCI - Nova", "lat": "38.8462", "id": "14122", "d": 15.87758843134814}, "download": 93080802.11759214, "ping": 21.193},{"bytes_received": 117163902, "timestamp": "2017-10-13T11:00:01.336240", "bytes_sent": 14991360, "upload": 11850693.895865561, "server": {"latency": 22.66, "name": "Reston, VA", "url": "http://speed1.iad2.inforelay.net/speedtest/upload.php", "country": "United States", "lon": "-77.3414", "cc": "US", "host": "speed1.iad2.inforelay.net:8080", "sponsor": "InfoRelay Online Systems", "url2": "http://67.208.74.124/speedtest/upload.php", "lat": "38.9686", "id": "1344", "d": 25.39058718521606}, "download": 93410879.57610838, "ping": 22.66},{"bytes_received": 117138596, "timestamp": "2017-10-13T11:15:01.265522", "bytes_sent": 14917632, "upload": 11850894.559492346, "server": {"latency": 19.446, "name": "Washington, DC", "url": "http://was.speedtest.sbcglobal.net/speedtest/upload.php", "country": "United States", "lon": "-77.0164", "cc": "US", "host": "was.speedtest.sbcglobal.net:8080", "sponsor": "AT&T", "lat": "38.9047", "id": "5113", "d": 14.199124910496671}, "download": 92891297.85772204, "ping": 19.446},{"bytes_received": 117007842, "timestamp": "2017-10-13T11:30:01.253796", "bytes_sent": 15163392, "upload": 11959641.531453518, "server": {"latency": 20.175, "name": "Washington, DC", "url": "http://was.speedtest.sbcglobal.net/speedtest/upload.php", "country": "United States", "lon": "-77.0164", "cc": "US", "host": "was.speedtest.sbcglobal.net:8080", "sponsor": "AT&T", "lat": "38.9047", "id": "5113", "d": 14.199124910496671}, "download": 92964188.95788565, "ping": 20.175},{"bytes_received": 117094682, "timestamp": "2017-10-13T11:45:01.212241", "bytes_sent": 15089664, "upload": 11848405.231565002, "server": {"latency": 18.84, "name": "Washington, DC", "url": "http://was.speedtest.sbcglobal.net/speedtest/upload.php", "country": "United States", "lon": "-77.0164", "cc": "US", "host": "was.speedtest.sbcglobal.net:8080", "sponsor": "AT&T", "lat": "38.9047", "id": "5113", "d": 14.199124910496671}, "download": 93155944.6752244, "ping": 18.84},{"bytes_received": 117163902, "timestamp": "2017-10-13T12:00:01.276691", "bytes_sent": 15040512, "upload": 11824984.963231463, "server": {"latency": 21.322, "name": "Fairfax, VA", "url": "http://speedtest.rdc.dc.cox.net/speedtest/upload.php", "country": "United States", "lon": "-77.3063", "cc": "US", "host": "speedtest.rd.dc.cox.net:8080", "sponsor": "CCI - Nova", "lat": "38.8462", "id": "14122", "d": 15.87758843134814}, "download": 93341738.50700454, "ping": 21.322},{"bytes_received": 117202402, "timestamp": "2017-10-13T12:15:01.116565", "bytes_sent": 15114240, "upload": 11894350.027476279, "server": {"latency": 21.394, "name": "Fairfax, VA", "url": "http://speedtest.rdc.dc.cox.net/speedtest/upload.php", "country": "United States", "lon": "-77.3063", "cc": "US", "host": "speedtest.rd.dc.cox.net:8080", "sponsor": "CCI - Nova", "lat": "38.8462", "id": "14122", "d": 15.87758843134814}, "download": 93264254.77874573, "ping": 21.394},{"bytes_received": 117166362, "timestamp": "2017-10-13T12:30:09.106638", "bytes_sent": 15040512, "upload": 11842655.94632887, "server": {"latency": 21.775, "name": "Reston, VA", "url": "http://speed1.iad2.inforelay.net/speedtest/upload.php", "country": "United States", "lon": "-77.3414", "cc": "US", "host": "speed1.iad2.inforelay.net:8080", "sponsor": "InfoRelay Online Systems", "url2": "http://67.208.74.124/speedtest/upload.php", "lat": "38.9686", "id": "1344", "d": 25.39058718521606}, "download": 93366440.29700908, "ping": 21.775},{"bytes_received": 116913316, "timestamp": "2017-10-13T12:45:01.313915", "bytes_sent": 15040512, "upload": 11921297.179290863, "server": {"latency": 20.353, "name": "Washington, DC", "url": "http://was.speedtest.sbcglobal.net/speedtest/upload.php", "country": "United States", "lon": "-77.0164", "cc": "US", "host": "was.speedtest.sbcglobal.net:8080", "sponsor": "AT&T", "lat": "38.9047", "id": "5113", "d": 14.199124910496671}, "download": 92729011.77723697, "ping": 20.353},{"bytes_received": 117153662, "timestamp": "2017-10-13T13:00:09.174158", "bytes_sent": 14893056, "upload": 11805193.597483765, "server": {"latency": 19.747, "name": "Washington, DC", "url": "http://was.speedtest.sbcglobal.net/speedtest/upload.php", "country": "United States", "lon": "-77.0164", "cc": "US", "host": "was.speedtest.sbcglobal.net:8080", "sponsor": "AT&T", "lat": "38.9047", "id": "5113", "d": 14.199124910496671}, "download": 93183331.90623753, "ping": 19.747},{"bytes_received": 117148836, "timestamp": "2017-10-13T13:15:01.156667", "bytes_sent": 14516224, "upload": 11384922.133839475, "server": {"latency": 21.438, "name": "Reston, VA", "url": "http://speed1.iad2.inforelay.net/speedtest/upload.php", "country": "United States", "lon": "-77.3414", "cc": "US", "host": "speed1.iad2.inforelay.net:8080", "sponsor": "InfoRelay Online Systems", "url2": "http://67.208.74.124/speedtest/upload.php", "lat": "38.9686", "id": "1344", "d": 25.39058718521606}, "download": 93305752.49567552, "ping": 21.438},{"bytes_received": 117151202, "timestamp": "2017-10-13T13:30:01.260607", "bytes_sent": 15097856, "upload": 11862059.706431387, "server": {"latency": 20.572, "name": "Reston, VA", "url": "http://speed1.iad2.inforelay.net/speedtest/upload.php", "country": "United States", "lon": "-77.3414", "cc": "US", "host": "speed1.iad2.inforelay.net:8080", "sponsor": "InfoRelay Online Systems", "url2": "http://67.208.74.124/speedtest/upload.php", "lat": "38.9686", "id": "1344", "d": 25.39058718521606}, "download": 93200317.56448744, "ping": 20.572},{"bytes_received": 116767496, "timestamp": "2017-10-13T13:45:01.300653", "bytes_sent": 15097856, "upload": 11960203.883893188, "server": {"latency": 19.459, "name": "Washington, DC", "url": "http://was.speedtest.sbcglobal.net/speedtest/upload.php", "country": "United States", "lon": "-77.0164", "cc": "US", "host": "was.speedtest.sbcglobal.net:8080", "sponsor": "AT&T", "lat": "38.9047", "id": "5113", "d": 14.199124910496671}, "download": 92545989.80713047, "ping": 19.459},{"bytes_received": 116948368, "timestamp": "2017-10-13T14:00:01.376498", "bytes_sent": 15122432, "upload": 11884168.475013917, "server": {"latency": 19.462, "name": "Washington, DC", "url": "http://was.speedtest.sbcglobal.net/speedtest/upload.php", "country": "United States", "lon": "-77.0164", "cc": "US", "host": "was.speedtest.sbcglobal.net:8080", "sponsor": "AT&T", "lat": "38.9047", "id": "5113", "d": 14.199124910496671}, "download": 93260595.63854939, "ping": 19.462},{"bytes_received": 117068788, "timestamp": "2017-10-13T14:15:01.196198", "bytes_sent": 15040512, "upload": 11905520.539473148, "server": {"latency": 19.39, "name": "Washington, DC", "url": "http://was.speedtest.sbcglobal.net/speedtest/upload.php", "country": "United States", "lon": "-77.0164", "cc": "US", "host": "was.speedtest.sbcglobal.net:8080", "sponsor": "AT&T", "lat": "38.9047", "id": "5113", "d": 14.199124910496671}, "download": 93442476.42701785, "ping": 19.39},{"bytes_received": 117148836, "timestamp": "2017-10-13T14:30:01.217036", "bytes_sent": 14925824, "upload": 11857456.645645808, "server": {"latency": 19.202, "name": "Washington, DC", "url": "http://was.speedtest.sbcglobal.net/speedtest/upload.php", "country": "United States", "lon": "-77.0164", "cc": "US", "host": "was.speedtest.sbcglobal.net:8080", "sponsor": "AT&T", "lat": "38.9047", "id": "5113", "d": 14.199124910496671}, "download": 92564630.52390732, "ping": 19.202},{"bytes_received": 117151202, "timestamp": "2017-10-13T14:45:01.333210", "bytes_sent": 15040512, "upload": 9549854.959940234, "server": {"latency": 21.453, "name": "Reston, VA", "url": "http://speed1.iad2.inforelay.net/speedtest/upload.php", "country": "United States", "lon": "-77.3414", "cc": "US", "host": "speed1.iad2.inforelay.net:8080", "sponsor": "InfoRelay Online Systems", "url2": "http://67.208.74.124/speedtest/upload.php", "lat": "38.9686", "id": "1344", "d": 25.39058718521606}, "download": 93206341.66300169, "ping": 21.453},{"bytes_received": 117077156, "timestamp": "2017-10-13T15:00:01.369458", "bytes_sent": 15097856, "upload": 11856381.869728362, "server": {"latency": 20.56, "name": "Washington, DC", "url": "http://was.speedtest.sbcglobal.net/speedtest/upload.php", "country": "United States", "lon": "-77.0164", "cc": "US", "host": "was.speedtest.sbcglobal.net:8080", "sponsor": "AT&T", "lat": "38.9047", "id": "5113", "d": 14.199124910496671}, "download": 93392502.6809868, "ping": 20.56},{"bytes_received": 116708516, "timestamp": "2017-10-13T15:15:01.267801", "bytes_sent": 14655488, "upload": 11552043.321188036, "server": {"latency": 19.521, "name": "Washington, DC", "url": "http://was.speedtest.sbcglobal.net/speedtest/upload.php", "country": "United States", "lon": "-77.0164", "cc": "US", "host": "was.speedtest.sbcglobal.net:8080", "sponsor": "AT&T", "lat": "38.9047", "id": "5113", "d": 14.199124910496671}, "download": 92843757.82460563, "ping": 19.521},{"bytes_received": 112866056, "timestamp": "2017-10-13T15:30:08.428854", "bytes_sent": 15097856, "upload": 11958854.045670124, "server": {"latency": 20.148, "name": "Washington, DC", "url": "http://was.speedtest.sbcglobal.net/speedtest/upload.php", "country": "United States", "lon": "-77.0164", "cc": "US", "host": "was.speedtest.sbcglobal.net:8080", "sponsor": "AT&T", "lat": "38.9047", "id": "5113", "d": 14.199124910496671}, "download": 89520319.520689, "ping": 20.148},{"bytes_received": 115226082, "timestamp": "2017-10-13T15:45:01.168218", "bytes_sent": 15024128, "upload": 11832081.046366943, "server": {"latency": 20.153, "name": "Washington, DC", "url": "http://was.speedtest.sbcglobal.net/speedtest/upload.php", "country": "United States", "lon": "-77.0164", "cc": "US", "host": "was.speedtest.sbcglobal.net:8080", "sponsor": "AT&T", "lat": "38.9047", "id": "5113", "d": 14.199124910496671}, "download": 91770294.40689717, "ping": 20.153},{"bytes_received": 117159076, "timestamp": "2017-10-13T16:00:01.233113", "bytes_sent": 15138816, "upload": 9347361.388888363, "server": {"latency": 19.792, "name": "Washington, DC", "url": "http://was.speedtest.sbcglobal.net/speedtest/upload.php", "country": "United States", "lon": "-77.0164", "cc": "US", "host": "was.speedtest.sbcglobal.net:8080", "sponsor": "AT&T", "lat": "38.9047", "id": "5113", "d": 14.199124910496671}, "download": 93202299.23354867, "ping": 19.792},{"bytes_received": 117204862, "timestamp": "2017-10-13T16:15:01.300128", "bytes_sent": 15081472, "upload": 11885311.241153197, "server": {"latency": 20.747, "name": "Fairfax, VA", "url": "http://speedtest.rdc.dc.cox.net/speedtest/upload.php", "country": "United States", "lon": "-77.3063", "cc": "US", "host": "speedtest.rd.dc.cox.net:8080", "sponsor": "CCI - Nova", "lat": "38.8462", "id": "14122", "d": 15.87758843134814}, "download": 93460257.1384827, "ping": 20.747},{"bytes_received": 117215102, "timestamp": "2017-10-13T16:30:01.234055", "bytes_sent": 14180352, "upload": 11164384.33953696, "server": {"latency": 21.194, "name": "Fairfax, VA", "url": "http://speedtest.rdc.dc.cox.net/speedtest/upload.php", "country": "United States", "lon": "-77.3063", "cc": "US", "host": "speedtest.rd.dc.cox.net:8080", "sponsor": "CCI - Nova", "lat": "38.8462", "id": "14122", "d": 15.87758843134814}, "download": 93474273.73487645, "ping": 21.194},{"bytes_received": 117135642, "timestamp": "2017-10-13T16:45:01.230156", "bytes_sent": 15097856, "upload": 11874108.255207831, "server": {"latency": 19.145, "name": "Washington, DC", "url": "http://was.speedtest.sbcglobal.net/speedtest/upload.php", "country": "United States", "lon": "-77.0164", "cc": "US", "host": "was.speedtest.sbcglobal.net:8080", "sponsor": "AT&T", "lat": "38.9047", "id": "5113", "d": 14.199124910496671}, "download": 93416222.64077328, "ping": 19.145},{"bytes_received": 117156616, "timestamp": "2017-10-13T17:00:02.124927", "bytes_sent": 15114240, "upload": 11915503.618581137, "server": {"latency": 19.505, "name": "Washington, DC", "url": "http://was.speedtest.sbcglobal.net/speedtest/upload.php", "country": "United States", "lon": "-77.0164", "cc": "US", "host": "was.speedtest.sbcglobal.net:8080", "sponsor": "AT&T", "lat": "38.9047", "id": "5113", "d": 14.199124910496671}, "download": 93192500.96175645, "ping": 19.505},{"bytes_received": 117115656, "timestamp": "2017-10-13T17:15:01.178827", "bytes_sent": 15106048, "upload": 11978419.54118454, "server": {"latency": 19.617, "name": "Washington, DC", "url": "http://was.speedtest.sbcglobal.net/speedtest/upload.php", "country": "United States", "lon": "-77.0164", "cc": "US", "host": "was.speedtest.sbcglobal.net:8080", "sponsor": "AT&T", "lat": "38.9047", "id": "5113", "d": 14.199124910496671}, "download": 93227912.69428091, "ping": 19.617},{"bytes_received": 117015716, "timestamp": "2017-10-13T17:30:01.284970", "bytes_sent": 15073280, "upload": 11847431.580429066, "server": {"latency": 20.326, "name": "Reston, VA", "url": "http://speed1.iad2.inforelay.net/speedtest/upload.php", "country": "United States", "lon": "-77.3414", "cc": "US", "host": "speed1.iad2.inforelay.net:8080", "sponsor": "InfoRelay Online Systems", "url2": "http://67.208.74.124/speedtest/upload.php", "lat": "38.9686", "id": "1344", "d": 25.39058718521606}, "download": 92703595.27729917, "ping": 20.326},{"bytes_received": 111250502, "timestamp": "2017-10-13T17:45:01.202879", "bytes_sent": 14991360, "upload": 11877046.845592758, "server": {"latency": 19.14, "name": "Washington, DC", "url": "http://was.speedtest.sbcglobal.net/speedtest/upload.php", "country": "United States", "lon": "-77.0164", "cc": "US", "host": "was.speedtest.sbcglobal.net:8080", "sponsor": "AT&T", "lat": "38.9047", "id": "5113", "d": 14.199124910496671}, "download": 88596005.14734767, "ping": 19.14},{"bytes_received": 117146376, "timestamp": "2017-10-13T18:00:01.275926", "bytes_sent": 15081472, "upload": 11815381.522803979, "server": {"latency": 19.696, "name": "Washington, DC", "url": "http://was.speedtest.sbcglobal.net/speedtest/upload.php", "country": "United States", "lon": "-77.0164", "cc": "US", "host": "was.speedtest.sbcglobal.net:8080", "sponsor": "AT&T", "lat": "38.9047", "id": "5113", "d": 14.199124910496671}, "download": 93185709.70277126, "ping": 19.696},{"bytes_received": 117204862, "timestamp": "2017-10-13T18:15:01.206820", "bytes_sent": 13869056, "upload": 11000052.461963428, "server": {"latency": 21.419, "name": "Fairfax, VA", "url": "http://speedtest.rdc.dc.cox.net/speedtest/upload.php", "country": "United States", "lon": "-77.3063", "cc": "US", "host": "speedtest.rd.dc.cox.net:8080", "sponsor": "CCI - Nova", "lat": "38.8462", "id": "14122", "d": 15.87758843134814}, "download": 93376758.11828801, "ping": 21.419},{"bytes_received": 117204368, "timestamp": "2017-10-13T18:30:10.624610", "bytes_sent": 15007744, "upload": 11772506.275452474, "server": {"latency": 21.977, "name": "Reston, VA", "url": "http://speed1.iad2.inforelay.net/speedtest/upload.php", "country": "United States", "lon": "-77.3414", "cc": "US", "host": "speed1.iad2.inforelay.net:8080", "sponsor": "InfoRelay Online Systems", "url2": "http://67.208.74.124/speedtest/upload.php", "lat": "38.9686", "id": "1344", "d": 25.39058718521606}, "download": 93414393.98668145, "ping": 21.977},{"bytes_received": 116534436, "timestamp": "2017-10-13T18:45:01.322277", "bytes_sent": 14893056, "upload": 11818241.872616623, "server": {"latency": 19.23, "name": "Washington, DC", "url": "http://was.speedtest.sbcglobal.net/speedtest/upload.php", "country": "United States", "lon": "-77.0164", "cc": "US", "host": "was.speedtest.sbcglobal.net:8080", "sponsor": "AT&T", "lat": "38.9047", "id": "5113", "d": 14.199124910496671}, "download": 92729221.73459366, "ping": 19.23},{"bytes_received": 116948862, "timestamp": "2017-10-13T19:00:01.330022", "bytes_sent": 14999552, "upload": 11905130.11975216, "server": {"latency": 19.794, "name": "Washington, DC", "url": "http://was.speedtest.sbcglobal.net/speedtest/upload.php", "country": "United States", "lon": "-77.0164", "cc": "US", "host": "was.speedtest.sbcglobal.net:8080", "sponsor": "AT&T", "lat": "38.9047", "id": "5113", "d": 14.199124910496671}, "download": 93343196.24872911, "ping": 19.794},{"bytes_received": 117081982, "timestamp": "2017-10-13T19:15:01.295694", "bytes_sent": 15097856, "upload": 11892370.114651091, "server": {"latency": 19.891, "name": "Washington, DC", "url": "http://was.speedtest.sbcglobal.net/speedtest/upload.php", "country": "United States", "lon": "-77.0164", "cc": "US", "host": "was.speedtest.sbcglobal.net:8080", "sponsor": "AT&T", "lat": "38.9047", "id": "5113", "d": 14.199124910496671}, "download": 93405898.60933755, "ping": 19.891},{"bytes_received": 115638142, "timestamp": "2017-10-13T19:30:01.343205", "bytes_sent": 10723328, "upload": 8398876.787249483, "server": {"latency": 20.005, "name": "Washington, DC", "url": "http://was.speedtest.sbcglobal.net/speedtest/upload.php", "country": "United States", "lon": "-77.0164", "cc": "US", "host": "was.speedtest.sbcglobal.net:8080", "sponsor": "AT&T", "lat": "38.9047", "id": "5113", "d": 14.199124910496671}, "download": 91996282.0059142, "ping": 20.005},{"bytes_received": 116040456, "timestamp": "2017-10-13T19:45:01.300490", "bytes_sent": 15024128, "upload": 9382011.487322247, "server": {"latency": 19.491, "name": "Washington, DC", "url": "http://was.speedtest.sbcglobal.net/speedtest/upload.php", "country": "United States", "lon": "-77.0164", "cc": "US", "host": "was.speedtest.sbcglobal.net:8080", "sponsor": "AT&T", "lat": "38.9047", "id": "5113", "d": 14.199124910496671}, "download": 92521944.62983246, "ping": 19.491},{"bytes_received": 104658402, "timestamp": "2017-10-13T20:00:01.424321", "bytes_sent": 14753792, "upload": 11673599.078962281, "server": {"latency": 19.444, "name": "Washington, DC", "url": "http://was.speedtest.sbcglobal.net/speedtest/upload.php", "country": "United States", "lon": "-77.0164", "cc": "US", "host": "was.speedtest.sbcglobal.net:8080", "sponsor": "AT&T", "lat": "38.9047", "id": "5113", "d": 14.199124910496671}, "download": 83438791.10406958, "ping": 19.444},{"bytes_received": 117181922, "timestamp": "2017-10-13T20:15:01.314533", "bytes_sent": 15073280, "upload": 11780461.512801908, "server": {"latency": 21.48, "name": "Fairfax, VA", "url": "http://speedtest.rdc.dc.cox.net/speedtest/upload.php", "country": "United States", "lon": "-77.3063", "cc": "US", "host": "speedtest.rd.dc.cox.net:8080", "sponsor": "CCI - Nova", "lat": "38.8462", "id": "14122", "d": 15.87758843134814}, "download": 93269415.51098423, "ping": 21.48},{"bytes_received": 117107876, "timestamp": "2017-10-13T20:30:08.029436", "bytes_sent": 14843904, "upload": 11822362.192580035, "server": {"latency": 19.885, "name": "Washington, DC", "url": "http://was.speedtest.sbcglobal.net/speedtest/upload.php", "country": "United States", "lon": "-77.0164", "cc": "US", "host": "was.speedtest.sbcglobal.net:8080", "sponsor": "AT&T", "lat": "38.9047", "id": "5113", "d": 14.199124910496671}, "download": 92748914.72957319, "ping": 19.885},{"bytes_received": 117089268, "timestamp": "2017-10-13T20:45:01.169454", "bytes_sent": 15056896, "upload": 11883683.751656199, "server": {"latency": 20.689, "name": "Fairfax, VA", "url": "http://speedtest.rdc.dc.cox.net/speedtest/upload.php", "country": "United States", "lon": "-77.3063", "cc": "US", "host": "speedtest.rd.dc.cox.net:8080", "sponsor": "CCI - Nova", "lat": "38.8462", "id": "14122", "d": 15.87758843134814}, "download": 93403216.94857061, "ping": 20.689},{"bytes_received": 117179462, "timestamp": "2017-10-13T21:00:07.227354", "bytes_sent": 15007744, "upload": 11850256.394360058, "server": {"latency": 20.582, "name": "Fairfax, VA", "url": "http://speedtest.rdc.dc.cox.net/speedtest/upload.php", "country": "United States", "lon": "-77.3063", "cc": "US", "host": "speedtest.rd.dc.cox.net:8080", "sponsor": "CCI - Nova", "lat": "38.8462", "id": "14122", "d": 15.87758843134814}, "download": 93253021.77690963, "ping": 20.582},{"bytes_received": 117115162, "timestamp": "2017-10-13T21:15:01.286696", "bytes_sent": 14983168, "upload": 11755749.110186342, "server": {"latency": 19.746, "name": "Washington, DC", "url": "http://was.speedtest.sbcglobal.net/speedtest/upload.php", "country": "United States", "lon": "-77.0164", "cc": "US", "host": "was.speedtest.sbcglobal.net:8080", "sponsor": "AT&T", "lat": "38.9047", "id": "5113", "d": 14.199124910496671}, "download": 93206384.86518484, "ping": 19.746},{"bytes_received": 108831496, "timestamp": "2017-10-13T21:30:07.764369", "bytes_sent": 15007744, "upload": 11908832.079829818, "server": {"latency": 19.44, "name": "Washington, DC", "url": "http://was.speedtest.sbcglobal.net/speedtest/upload.php", "country": "United States", "lon": "-77.0164", "cc": "US", "host": "was.speedtest.sbcglobal.net:8080", "sponsor": "AT&T", "lat": "38.9047", "id": "5113", "d": 14.199124910496671}, "download": 86689390.18822949, "ping": 19.44},{"bytes_received": 116982042, "timestamp": "2017-10-13T21:45:01.202598", "bytes_sent": 15007744, "upload": 11900691.89190166, "server": {"latency": 19.581, "name": "Washington, DC", "url": "http://was.speedtest.sbcglobal.net/speedtest/upload.php", "country": "United States", "lon": "-77.0164", "cc": "US", "host": "was.speedtest.sbcglobal.net:8080", "sponsor": "AT&T", "lat": "38.9047", "id": "5113", "d": 14.199124910496671}, "download": 93280430.32206906, "ping": 19.581},{"bytes_received": 117204862, "timestamp": "2017-10-13T22:00:08.223912", "bytes_sent": 14917632, "upload": 11849987.242067635, "server": {"latency": 21.327, "name": "Reston, VA", "url": "http://speed1.iad2.inforelay.net/speedtest/upload.php", "country": "United States", "lon": "-77.3414", "cc": "US", "host": "speed1.iad2.inforelay.net:8080", "sponsor": "InfoRelay Online Systems", "url2": "http://67.208.74.124/speedtest/upload.php", "lat": "38.9686", "id": "1344", "d": 25.39058718521606}, "download": 93468155.86138561, "ping": 21.327},{"bytes_received": 117189208, "timestamp": "2017-10-13T22:15:01.257463", "bytes_sent": 15081472, "upload": 11865143.071308294, "server": {"latency": 20.807, "name": "Fairfax, VA", "url": "http://speedtest.rdc.dc.cox.net/speedtest/upload.php", "country": "United States", "lon": "-77.3063", "cc": "US", "host": "speedtest.rd.dc.cox.net:8080", "sponsor": "CCI - Nova", "lat": "38.8462", "id": "14122", "d": 15.87758843134814}, "download": 93246009.21594936, "ping": 20.807},{"bytes_received": 115896602, "timestamp": "2017-10-13T22:30:04.517908", "bytes_sent": 15138816, "upload": 11942648.32212753, "server": {"latency": 19.104, "name": "Washington, DC", "url": "http://was.speedtest.sbcglobal.net/speedtest/upload.php", "country": "United States", "lon": "-77.0164", "cc": "US", "host": "was.speedtest.sbcglobal.net:8080", "sponsor": "AT&T", "lat": "38.9047", "id": "5113", "d": 14.199124910496671}, "download": 92270011.27001525, "ping": 19.104},{"bytes_received": 117023002, "timestamp": "2017-10-13T22:45:01.208873", "bytes_sent": 15138816, "upload": 11860912.299901206, "server": {"latency": 18.988, "name": "Washington, DC", "url": "http://was.speedtest.sbcglobal.net/speedtest/upload.php", "country": "United States", "lon": "-77.0164", "cc": "US", "host": "was.speedtest.sbcglobal.net:8080", "sponsor": "AT&T", "lat": "38.9047", "id": "5113", "d": 14.199124910496671}, "download": 93214966.06481357, "ping": 18.988},{"bytes_received": 117186254, "timestamp": "2017-10-13T23:00:01.271852", "bytes_sent": 15106048, "upload": 11930931.717925793, "server": {"latency": 21.219, "name": "Fairfax, VA", "url": "http://speedtest.rdc.dc.cox.net/speedtest/upload.php", "country": "United States", "lon": "-77.3063", "cc": "US", "host": "speedtest.rd.dc.cox.net:8080", "sponsor": "CCI - Nova", "lat": "38.8462", "id": "14122", "d": 15.87758843134814}, "download": 93367178.26268774, "ping": 21.219},{"bytes_received": 117112702, "timestamp": "2017-10-13T23:15:01.287808", "bytes_sent": 15097856, "upload": 9290236.412277672, "server": {"latency": 20.209, "name": "Washington, DC", "url": "http://was.speedtest.sbcglobal.net/speedtest/upload.php", "country": "United States", "lon": "-77.0164", "cc": "US", "host": "was.speedtest.sbcglobal.net:8080", "sponsor": "AT&T", "lat": "38.9047", "id": "5113", "d": 14.199124910496671}, "download": 93161452.03969467, "ping": 20.209},{"error":true},{"bytes_received": 117077156, "timestamp": "2017-10-13T23:45:01.447995", "bytes_sent": 14802944, "upload": 11738298.555540485, "server": {"latency": 19.5, "name": "Washington, DC", "url": "http://was.speedtest.sbcglobal.net/speedtest/upload.php", "country": "United States", "lon": "-77.0164", "cc": "US", "host": "was.speedtest.sbcglobal.net:8080", "sponsor": "AT&T", "lat": "38.9047", "id": "5113", "d": 14.199124910496671}, "download": 93287259.42633952, "ping": 19.5},{"bytes_received": 117135642, "timestamp": "2017-10-14T00:00:01.299038", "bytes_sent": 15122432, "upload": 9632356.926975869, "server": {"latency": 19.283, "name": "Washington, DC", "url": "http://was.speedtest.sbcglobal.net/speedtest/upload.php", "country": "United States", "lon": "-77.0164", "cc": "US", "host": "was.speedtest.sbcglobal.net:8080", "sponsor": "AT&T", "lat": "38.9047", "id": "5113", "d": 14.199124910496671}, "download": 93194545.38358201, "ping": 19.283},{"bytes_received": 117107876, "timestamp": "2017-10-14T00:15:01.132493", "bytes_sent": 15015936, "upload": 11900929.033840837, "server": {"latency": 19.117, "name": "Washington, DC", "url": "http://was.speedtest.sbcglobal.net/speedtest/upload.php", "country": "United States", "lon": "-77.0164", "cc": "US", "host": "was.speedtest.sbcglobal.net:8080", "sponsor": "AT&T", "lat": "38.9047", "id": "5113", "d": 14.199124910496671}, "download": 93170554.52440201, "ping": 19.117},{"bytes_received": 117150708, "timestamp": "2017-10-14T00:30:01.257461", "bytes_sent": 15065088, "upload": 11809355.062635804, "server": {"latency": 20.298, "name": "Reston, VA", "url": "http://speed1.iad2.inforelay.net/speedtest/upload.php", "country": "United States", "lon": "-77.3414", "cc": "US", "host": "speed1.iad2.inforelay.net:8080", "sponsor": "InfoRelay Online Systems", "url2": "http://67.208.74.124/speedtest/upload.php", "lat": "38.9686", "id": "1344", "d": 25.39058718521606}, "download": 93174453.50612934, "ping": 20.298},{"bytes_received": 117077156, "timestamp": "2017-10-14T00:45:01.254376", "bytes_sent": 15130624, "upload": 11836471.651891842, "server": {"latency": 19.738, "name": "Washington, DC", "url": "http://was.speedtest.sbcglobal.net/speedtest/upload.php", "country": "United States", "lon": "-77.0164", "cc": "US", "host": "was.speedtest.sbcglobal.net:8080", "sponsor": "AT&T", "lat": "38.9047", "id": "5113", "d": 14.199124910496671}, "download": 92991304.75741403, "ping": 19.738},{"bytes_received": 117178968, "timestamp": "2017-10-14T01:00:01.334003", "bytes_sent": 15089664, "upload": 11864946.452466642, "server": {"latency": 19.499, "name": "Washington, DC", "url": "http://was.speedtest.sbcglobal.net/speedtest/upload.php", "country": "United States", "lon": "-77.0164", "cc": "US", "host": "was.speedtest.sbcglobal.net:8080", "sponsor": "AT&T", "lat": "38.9047", "id": "5113", "d": 14.199124910496671}, "download": 93329751.7860671, "ping": 19.499},{"bytes_received": 115573748, "timestamp": "2017-10-14T01:15:01.237143", "bytes_sent": 15097856, "upload": 11962861.25339837, "server": {"latency": 19.307, "name": "Washington, DC", "url": "http://was.speedtest.sbcglobal.net/speedtest/upload.php", "country": "United States", "lon": "-77.0164", "cc": "US", "host": "was.speedtest.sbcglobal.net:8080", "sponsor": "AT&T", "lat": "38.9047", "id": "5113", "d": 14.199124910496671}, "download": 91663931.52793433, "ping": 19.307},{"bytes_received": 117110242, "timestamp": "2017-10-14T01:30:01.375164", "bytes_sent": 15065088, "upload": 11882279.717019506, "server": {"latency": 20.391, "name": "Washington, DC", "url": "http://was.speedtest.sbcglobal.net/speedtest/upload.php", "country": "United States", "lon": "-77.0164", "cc": "US", "host": "was.speedtest.sbcglobal.net:8080", "sponsor": "AT&T", "lat": "38.9047", "id": "5113", "d": 14.199124910496671}, "download": 93491412.23044433, "ping": 20.391},{"bytes_received": 117145294, "timestamp": "2017-10-14T01:45:01.267562", "bytes_sent": 14704640, "upload": 11670449.772116235, "server": {"latency": 20.807, "name": "Fairfax, VA", "url": "http://speedtest.rdc.dc.cox.net/speedtest/upload.php", "country": "United States", "lon": "-77.3063", "cc": "US", "host": "speedtest.rd.dc.cox.net:8080", "sponsor": "CCI - Nova", "lat": "38.8462", "id": "14122", "d": 15.87758843134814}, "download": 92881094.49375826, "ping": 20.807},{"bytes_received": 117143422, "timestamp": "2017-10-14T02:00:01.326673", "bytes_sent": 15106048, "upload": 11949668.498829504, "server": {"latency": 19.249, "name": "Washington, DC", "url": "http://was.speedtest.sbcglobal.net/speedtest/upload.php", "country": "United States", "lon": "-77.0164", "cc": "US", "host": "was.speedtest.sbcglobal.net:8080", "sponsor": "AT&T", "lat": "38.9047", "id": "5113", "d": 14.199124910496671}, "download": 93193089.65040542, "ping": 19.249}]}
