{"speedlogs":[
{"bytes_received": 117132304, "timestamp": "2018-02-13T05:00:58.078646", "bytes_sent": 15130624, "upload": 11907373.770526502, "server": {"latency": 21.859, "name": "Reston, VA", "url": "http://speed1.iad2.inforelay.net/speedtest/upload.php", "country": "United States", "lon": "-77.3414", "cc": "US", "host": "speed1.iad2.inforelay.net:8080", "sponsor": "InfoRelay Online Systems", "url2": "http://67.208.74.124/speedtest/upload.php", "lat": "38.9686", "id": "1344", "d": 25.39058718521606}, "download": 93300154.85832052, "ping": 21.859},{"bytes_received": 117079522, "timestamp": "2018-02-13T05:15:58.125638", "bytes_sent": 15024128, "upload": 11868592.667860998, "server": {"latency": 23.694, "name": "Reston, VA", "url": "http://speed1.iad2.inforelay.net/speedtest/upload.php", "country": "United States", "lon": "-77.3414", "cc": "US", "host": "speed1.iad2.inforelay.net:8080", "sponsor": "InfoRelay Online Systems", "url2": "http://67.208.74.124/speedtest/upload.php", "lat": "38.9686", "id": "1344", "d": 25.39058718521606}, "download": 93172867.20429577, "ping": 23.694},{"bytes_received": 117061008, "timestamp": "2018-02-13T05:30:57.914492", "bytes_sent": 15147008, "upload": 11901828.606892383, "server": {"latency": 21.376, "name": "Reston, VA", "url": "http://speed1.iad2.inforelay.net/speedtest/upload.php", "country": "United States", "lon": "-77.3414", "cc": "US", "host": "speed1.iad2.inforelay.net:8080", "sponsor": "InfoRelay Online Systems", "url2": "http://67.208.74.124/speedtest/upload.php", "lat": "38.9686", "id": "1344", "d": 25.39058718521606}, "download": 93292957.59818715, "ping": 21.376},{"bytes_received": 117140962, "timestamp": "2018-02-13T05:45:57.909803", "bytes_sent": 15163392, "upload": 11948529.395784467, "server": {"latency": 21.279, "name": "Reston, VA", "url": "http://speed1.iad2.inforelay.net/speedtest/upload.php", "country": "United States", "lon": "-77.3414", "cc": "US", "host": "speed1.iad2.inforelay.net:8080", "sponsor": "InfoRelay Online Systems", "url2": "http://67.208.74.124/speedtest/upload.php", "lat": "38.9686", "id": "1344", "d": 25.39058718521606}, "download": 93227289.33718525, "ping": 21.279},{"bytes_received": 116889882, "timestamp": "2018-02-13T06:00:58.032226", "bytes_sent": 14974976, "upload": 11828481.456184376, "server": {"latency": 21.634, "name": "Washington, DC", "url": "http://was.speedtest.sbcglobal.net/speedtest/upload.php", "country": "United States", "lon": "-77.0164", "cc": "US", "host": "was.speedtest.sbcglobal.net:8080", "sponsor": "AT&T", "lat": "38.9047", "id": "5113", "d": 14.199124910496671}, "download": 92987076.60259758, "ping": 21.634}]}
